Workbook

Sheet Combined, overhead
A1: Base overnight cost
B2: 1999 | C2: 2000 | D2: 2001 | E2: 2002 | F2: 2003 | G2: 2004 | H2: 2005 | I2: 2006 | J2: 2007 | K2: 2008 | L2: 2009 | M2: 2010 | N2: 2011 | O2: 2012 | P2: 2013 | Q2: 2014 | R2: 2015 | S2: 2016 | T2: 2017 | U2: 2018 | V2: 2019 | W2: 2020 | X2: 2021 | Y2: 2022
A3: Scrubbed Coal New | B3: 1093 | C3: 1102 | D3: 1021 | Q3: 2734 | R3: 2726
A4: Integrated Coal- Gasification Comb Cycle (IGCC) | B4: 1091 | C4: 1315 | D4: 1220 | Q4: 3525 | R4: 3483
A5: Conv Gas/Oil Comb Cycle | B5: 445 | C5: 449 | D5: 424 | Q5: 871 | R5: 869 | S5: 956 | T5: 923 | U5: 935 | V5: 952
A6: Combined-cycle—single shaft | W6: 1079 | X6: 1082 | Y6: 1201
A7: Adv Gas/Oil Comb Cycle (CC) | B7: 405 | C7: 580 | D7: 533 | Q7: 945 | R7: 942 | S7: 1080 | T7: 1013 | U7: 1026 | V7: 736
A8: Combined-cycle—multi shaft | W8: 954 | X8: 957 | Y8: 1062
A9: Conv Comb Turbine | B9: 329 | C9: 332 | D9: 315 | Q9: 924 | R9: 922 | S9: 1077 | T9: 1040 | U9: 1054 | V9: 1072
A10: Combustion turbine— aeroderivative8 | W10: 1170 | X10: 1169 | Y10: 1294
A11: Adv Comb Turbine | B11: 325 | C11: 465 | D11: 440 | Q11: 641 | R11: 639 | S11: 664 | T11: 640 | U11: 648 | V11: 658
A12: Combustion turbine—industrial frame | W12: 710 | X12: 709 | Y12: 785
A13: Adv Nuclear | B13: 1570 | C13: 2390 | D13: 1.729 | Q13: 4763 | R13: 4646 | S13: 6108 | T13: 5091 | U13: 5148 | V13: 5224 | W13: 6016 | X13: 6034 | Y13: 6695
A14: Conventional Hydropower | Q14: 2213 | R14: 2410 | S14: 2411 | T14: 2220 | U14: 2634 | V14: 2680 | W14: 2752 | X14: 2769 | Y14: 3083
A15: Wind | B15: 776 | C15: 993 | D15: 919 | Q15: 2061 | R15: 1850 | S15: 1644 | T15: 1576 | U15: 1548 | V15: 1518 | W15: 1319 | X15: 1846 | Y15: 1718
A16: Wind Offshore | Q16: 4503 | R16: 4476 | S16: 6331 | T16: 4648 | U16: 4694 | V16: 4758 | W16: 4356 | X16: 4362 | Y16: 4833
A17: Solar Thermal | B17: 1907 | C17: 3059 | D17: 2394 | Q17: 4715 | R17: 3787 | S17: 4168 | T17: 3908 | U17: 3952 | V17: 4011 | W17: 7191 | X17: 7116 | Y17: 7895
A18: Photovoltaic | B18: 2903 | C18: 4836 | D18: 3681 | Q18: 3394 | R18: 3123 | S18: 2480 | T18: 2169 | U18: 1763 | V18: 1876
A19: Photovoltaic tilting | U19: 2004 | V19: 1698 | W19: 1331 | X19: 1248 | Y19: 1327
A20: Solar PV with storage | X20: 1612 | Y20: 1748

Sheet Combined, O&M
A1: Fixed O&M cost
B2: 1999 | C2: 2000 | D2: 2001 | E2: 2002 | F2: 2003 | G2: 2004 | H2: 2005 | I2: 2006 | J2: 2007 | K2: 2008 | L2: 2009 | M2: 2010 | N2: 2011 | O2: 2012 | P2: 2013 | Q2: 2014 | R2: 2015 | S2: 2016 | T2: 2017 | U2: 2018 | V2: 2019 | W2: 2020 | X2: 2021 | Y2: 2022
A3: Scrubbed Coal New | B3: 23.03 | C3: 23.03 | Q3: 31.18 | R3: 31.16
A4: Integrated Coal- Gasification Comb Cycle (IGCC) | B4: 32.13 | C4: 32.13 | Q4: 51.39 | R4: 51.37
A5: Conv Gas/Oil Comb Cycle | B5: 15.35 | C5: 15.35 | Q5: 13.17 | R5: 13.16 | S5: 10.76 | T5: 10.93 | U5: 11.11 | V5: 11.33
A6: Combined-cycle—single shaft | W6: 14.04 | X6: 14.17 | Y6: 14.76
A7: Adv Gas/Oil Comb Cycle (CC) | B7: 14.23 | C7: 14.23 | Q7: 15.37 | R7: 15.36 | S7: 9.78 | T7: 9.94 | U7: 10.1 | V7: 10.3
A8: Combined-cycle—multi shaft | W8: 12.15 | X8: 12.26 | Y8: 12.77
A9: Conv Comb Turbine | B9: 6.35 | C9: 6.35 | Q9: 7.34 | R9: 7.34 | S9: 17.12 | T9: 17.39 | U9: 17.67 | V9: 18.03
A10: Combustion turbine— aeroderivative8 | W10: 16.23 | X10: 16.38 | Y10: 17.06
A11: Adv Comb Turbine | B11: 9.01 | C11: 9.01 | Q11: 7.04 | R11: 7.04 | S11: 6.65 | T11: 6.76 | U11: 6.87 | V11: 7.01
A12: Combustion turbine—industrial frame | W12: 6.97 | X12: 7.04 | Y12: 7.33
A13: Adv Nuclear | B13: 56.29 | C13: 56.29 | Q13: 93.28 | R13: 93.23 | S13: 98.11 | T13: 99.65 | U13: 101.28 | V13: 103.31 | W13: 121.13 | X13: 122.26 | Y13: 127.35
A14: Conventional Hydropower | Q14: 14.83 | R14: 15.15 | S14: 14.7 | T14: 14.93 | U14: 40.05 | V14: 40.85 | W14: 41.63 | X14: 42.01 | Y14: 43.78
A15: Wind | B15: 25.92 | C15: 25.92 | Q15: 39.55 | R15: 39.53 | S15: 45.98 | T15: 46.71 | U15: 47.47 | V15: 48.42 | W15: 26.22 | X15: 26.47 | Y15: 27.57
A16: Wind Offshore | Q16: 74 | R16: 73.96 | S16: 76.1 | T16: 77.3 | U16: 78.56 | V16: 80.14 | W16: 109.54 | X16: 110.56 | Y16: 115.16
A17: Solar Thermal | B17: 46.58 | C17: 46.58 | Q17: 67.26 | R17: 67.23 | S17: 69.17 | T17: 70.26 | U17: 71.41 | V17: 72.84 | W17: 85.03 | X17: 85.82 | Y17: 89.39
A18: Photovoltaic | B18: 9.82 | C18: 9.82 | Q18: 24.69 | R18: 24.68 | S18: 21.33 | T18: 21.66 | U18: 22.02 | V18: 22.46 | W18: 15.19
A19: Solar PV with storage | X19: 15.33 | Y19: 15.97
X20: 32.33 | Y20: 33.67
A26: Price year
B27: 1997 | C27: 1998

Sheet 2000
A1: Table 38. Cost and Performance Characteristics of New Electricity Generating Technologies
A2: Total Overnight Contingency Factors Cost Overnight including Variable Heatrate Heatrate Costs Contingencies O&M4 Fixed in in Online Size Leadtimes in 2001 in 20013 ($2000 O&M4 2001 2010 Technology Years1 (mW) (Years) ($2000/kW) (2000 $/kW) mills/kWh) ($2000/kW) (Btu/kWhr) (Btu/kWr)
A3: Conventional Pulverized Coal | C3: 2005 | D3: 400 | F3: 4 | G3: 1046 | I3: 1.07 | M3: 1 | O3: 1119 | Q3: 3.38 | S3: 23.41 | T3: 9386 | V3: 9087
A4: Integrated Coal- Gasification Combined | C4: 2005 | D4: 428 | F4: 4 | G4: 1250 | I4: 1.07 | M4: 1 | O4: 1338 | Q4: 0.8 | S4: 32.67 | T4: 7869 | V4: 6968
A5: Cycle Conventional Gas/Oil Combined Cycle | C5: 2004 | D5: 250 | F5: 3 | G5: 435 | I5: 1.05 | M5: 1 | O5: 456 | Q5: 0.52 | S5: 15.61 | T5: 7618 | V5: 7000
A6: Adv Gas/Oil Combined Cycle | C6: 2004 | D6: 400 | F6: 3 | G6: 546 | I6: 1.08 | M6: 1 | O6: 590 | Q6: 0.52 | S6: 14.46 | T6: 6870 | V6: 6350
A7: Conv Combustion Turbine5 | C7: 2002 | D7: 160 | F7: 2 | G7: 323 | I7: 1.05 | M7: 1 | O7: 339 | Q7: 0.1 | S7: 6.45 | T7: 11380 | V7: 10600
A8: Adv Combustion Turbine | C8: 2003 | D8: 120 | F8: 2 | G8: 451 | I8: 1.05 | M8: 1 | O8: 474 | Q8: 0.1 | S8: 9.16 | T8: 9020 | V8: 8000
A9: Fuel Cells | C9: 2004 | D9: 10 | F9: 3 | G9: 1810 | I9: 1.05 | M9: 1.1 | O9: 2091 | Q9: 2.08 | S9: 14.98 | T9: 5744 | V9: 5361
A10: Advanced Nuclear | C10: 2005 | D10: 600 | F10: 4 | G10: 1772 | I10: 1.1 | M10: 1.1 | O10: 2144 | Q10: 0.42 | S10: 57.23 | T10: 10400 | V10: 10400
A11: Generic Distributed Generation6 - Base Generic Distributed Generation6 - Peak
A12: 2004 | H12: 2 | K12: 3 | L12: 593 | N12: 1.05 | P12: 1 | R12: 623 | U12: 15.11 | W12: 4.02 | Y12: 10991 | AA12: 9210
A13: 2003 | H13: 1 | K13: 2 | L13: 533 | N13: 1.05 | P13: 1 | R13: 559 | U13: 23.1 | W13: 12.56 | Y13: 10620 | AA13: 10500
A14: Biomass | B14: 2005 | D14: 100 | F14: 4 | G14: 1536 | J14: 1.07 | M14: 1.05 | O14: 1725 | Q14: 2.9 | S14: 44.95 | T14: 8911 | V14: 8911
A15: MSW - Landfill Gas | B15: 2004 | D15: 30 | F15: 3 | G15: 1336 | J15: 1.07 | M15: 1 | O15: 1429 | Q15: 0.01 | S15: 96.31 | T15: 13648 | V15: 13648
A16: Geothermal 7,8 | B16: 2006 | D16: 50 | F16: 4 | G16: 1663 | J16: 1.05 | M16: 1 | O16: 1746 | Q16: 0 | S16: 70.07 | T16: 32173 | V16: 32173
A17: Wind | B17: 2004 | D17: 50 | F17: 3 | G17: 918 | J17: 1.07 | M17: 1 | O17: 982 | Q17: 0 | S17: 25.54 | T17: 10280 | V17: 10280
A18: Solar Thermal8 | B18: 2004 | D18: 100 | F18: 3 | G18: 2157 | J18: 1.07 | M18: 1.1 | O18: 2539 | Q18: 0 | S18: 47.87 | T18: 10280 | V18: 10280
A19: Solar Photovoltaic8 | B19: 2003 | D19: 5 | F19: 2 | G19: 3317 | J19: 1.05 | M19: 1.1 | O19: 3831 | Q19: 0 | S19: 9.85 | T19: 10280 | V19: 10280
A20: 1Online year represents the first year that a new unit could be completed, given an order date of 2001. 2The technological optimism factor is applied to the first four units of a new, unproven design. It reflects the demonstrated tendency to underestimate actual costs for a first-of-a-kind unit. 3Overnight capital cost including contingency factors, excluding regional multipliers and learning effects. Interest charges are also excluded. These represent costs of new projects initiated in 2001. 4O&M = Operation and maintenance. 5Combustion turbine units can be built by the model prior to 2003 if necessary to meet a given region’s reserve margin. 6The costs shown here are slightly different from costs shown in Table 41 because of updated adjustments for inflation. The unit size shown here is higher than that shown in Table 41 to reflect the minimum size that can be represented meaningfully in the model. The lead times are also different from those shown in Table 41 because lead times presented here include site acquisition, site preparation, and permitting for plants that are larger in size. 7Because geothermal cost and performance characteristics are specific for each site, the table entries represent the cost of the least expensive plant that could be built in the Northwest Power Pool region, where most of the proposed sites are located. 8Capital costs for geothermal and solar technologies are net of (reduced by) the ten percent investment tax credit.
A21: Source: Values are derived by the Energy Information Administration, Office of Integrated Analysis and Forecasting, from analysis of reports and discussions with various sources from industry, government, and the Department of Energy National Laboratories.
A22: Table 39. Regional Multipliers for Construction of Fossil-Fueled, Nuclear, and Renewable1 Generating Technologies
A23: EMM Region NE, NY | E23: MAAC | I23: STV | N23: MAPP, ECAR, MAIN | S23: SPP
A24: 1.043 | E24: 0.996 | I24: 0.96 | N24: 1.004 | S24: 0.997
A25: EMM Region RA | E25: NWP | I25: FL | N25: CNV | S25: ERCOT
A26: 1.003 | E26: 1.026 | I26: 0.961 | N26: 1.058 | S26: 0.986
A27: 1Regional multipliers are not applied to geothermal technologies because costs are site specific.
A28: Source: Argonne National Laboratory, Cost and Performance Database for Electric Power Generating Technologies..
A29: Technological Optimism and Learning Overnight costs for each technology are calculated as a function of regional construction parameters, project contingency, and technological optimism and learning factors. For each generating technology available for new capacity in a region, the overnight cost used by the model is calculated using the base cost, technological optimism and contingency factors for the technology from Table 38, the regional factors from Table 39, and the learning parameters from Table 40.

Sheet 1999
A1: Table 37. Cost and Performance Characteristics of New Central Station Electricity Generating Technologies
A2: Overnight Overnight Capital Capital Heatrate Heatrate Costs1 Costs1 Variable First- Nth-of-a- O&M Fixed First- Nth- Year Size Leadtime of-a-kind kind (1997 O&M of-a-kind of-a-kind Technology Available (mW) (Year) ($1997/kW) ($1997/kW) Mills/kWhr) ($1997/kW) (Btu/kWhr) (Btu/kWhr)
A3: Scrubbed Coal New | C3: 1997 | D3: 400 | E3: 4 | F3: 1093 | G3: 1093 | H3: 3.33 | I3: 23.03 | K3: 9585 | L3: 9087
A4: Integrated Gas Comb Cycle | C4: 1997 | D4: 428 | E4: 4 | F4: 1606 | G4: 1091 | H4: 0.79 | I4: 32.13 | K4: 8470 | L4: 6968
A5: Gas/Oil Steam Turbine | C5: 1997 | D5: 300 | E5: 2 | F5: 1004 | G5: 1004 | H5: 0.51 | I5: 30.7 | K5: 9500 | L5: 9500
A6: Conv Gas/Oil Comb Cycle | C6: 1997 | D6: 250 | E6: 3 | F6: 445 | G6: 445 | H6: 0.51 | I6: 15.35 | K6: 8030 | L6: 7000
A7: Adv Gas/Oil Comb Cycle | C7: 1997 | D7: 400 | E7: 3 | F7: 575 | G7: 405 | H7: 0.51 | I7: 14.23 | K7: 6985 | L7: 6350
A8: Conv Combustion Turbine | C8: 1998 | D8: 160 | E8: 2 | F8: 329 | G8: 329 | H8: 0.1 | I8: 6.35 | K8: 11900 | L8: 10600
A9: Adv Combustion Turbine | C9: 1997 | D9: 120 | E9: 2 | F9: 461 | G9: 325 | H9: 0.1 | I9: 9.01 | K9: 9700 | L9: 8000
A10: Fuel Cells | C10: 2001 | D10: 10 | E10: 2 | F10: 2146 | G10: 1458 | H10: 2.05 | I10: 14.74 | K10: 6000 | L10: 5361
A11: Advanced Nuclear | C11: 2001 | D11: 600 | E11: 4 | F11: 2371 | G11: 1570 | H11: 0.41 | I11: 56.29 | K11: 10400 | L11: 10400
A12: Biomass | C12: 2001 | D12: 100 | E12: 4 | F12: 2205 | G12: 1448 | H12: 5.32 | I12: 44 | K12: 9224 | L12: 8219
A13: MSW 2 | C13: 1996 | D13: 30 | E13: 1 | F13: N/A | G13: 5892 | H13: 5.532 | I13: 0 | K13: 16000 | L13: 16000
A14: Geothermal 3 | C14: 1997 | D14: 50 | E14: 4 | F14: 1831 | G14: 1831 | H14: 0 | I14: 85.9 | K14: 32391 | L14: N/A
A15: Wind | C15: 1997 | D15: 50 | E15: 3 | F15: 1109 | G15: 776 | H15: 0 | I15: 25.92 | K15: N/A | L15: N/A
A16: Solar Thermal4 ,5 | C16: 1997 | D16: 100 | E16: 3 | F16: 2904 | G16: 1907 | H16: 0 | I16: 46.58 | K16: N/A | L16: N/A
A17: Photovoltaic5 | C17: 1998 | D17: 5 | E17: 2 | F17: 4162 | G17: 2903 | H17: 0 | I17: 9.82 | K17: N/A | L17: N/A
A18: 1Overnight capital cost plus project contingencies, excluding regional multipliers (See Tables 38 and 39). 2Because municipal solid waste (MSW) does not compete with other technologies in the model, these values are used only in calculating the average costs of electricity. 3Because geothermal cost and performance parameters are specific for each of the 51 sites in the database, the Nth-of-a-kind capital cost and heatrate are averages for the capacity built in 2000. 4Solar thermal is assumed to operate economically only in Electricity Market Module regions 2, 5, and 10-13, that is, West of the Mississippi River, because of its requirement for significant direct, normal insolation. 5Capital costs for solar technologies are net of (reduced by) the 10 percent investment tax credit. O&M = Operation and maintenance. Sources: Most values are derived by the Energy Information Administration, Office of Integrated Analysis and Forecasting from analysis of reports and discussions with various sources from industry, government, and the National Laboratories, with the following specific sources — Solar Thermal: California Energy Commission Memorandum, Technology Characterization for ER94, August 6, 1993. Photovoltaic: Technical Assessment Guide-Electric Power Research Institute (EPRI-TAG1993). MSW: EPRI-TAG 1993.

Sheet 2011
A1: Table 8.2 Cost and performance characteristics of new central station electricity generating technologies
E2: Base Overnight Cost in 2010 (2009 $/ kW) | F2: Contingency Factors | H2: Total Overnight Cost in 20104 (2009 $/ kW) | L2: nth-of-a- kind Heatrate (Btu/ kWhr)
A3: Technology | B3: Online Year1 | C3: Size (mW) | D3: Lead time (years) | F3: Project Contin- gency Factor2 | G3: Techno logical Optimism Factor3 | I3: Variable O&M5 (2009 $/MWh) | J3: Fixed O&M (2009$/ kW) | K3: Heatrate6 in 2010 (Btu/ kWhr)
A4: Scrubbed Coal New7 | B4: 2014 | C4: 1300 | D4: 4 | E4: 2,625 | F4: 1.07 | G4: 1 | H4: 2,809 | I4: 4.2 | J4: 29.31 | K4: 8,800 | L4: 8,740
A5: Integrated Coal- Gasification Comb Cycle (IGCC)7 | B5: 2014 | C5: 1200 | D5: 4 | E5: 2,974 | F5: 1.07 | G5: 1 | H5: 3,182 | I5: 6.79 | J5: 58.52 | K5: 8,700 | L5: 7,450
A6: IGCC with carbon sequestration | B6: 2016 | C6: 520 | D6: 4 | E6: 4,797 | F6: 1.07 | G6: 1.03 | H6: 5,287 | I6: 8.83 | J6: 68.47 | K6: 10,700 | L6: 8,307
A7: Conv Gas/Oil Comb Cycle | B7: 2013 | C7: 540 | D7: 3 | E7: 921 | F7: 1.05 | G7: 1 | H7: 967 | I7: 3.37 | J7: 14.22 | K7: 7,050 | L7: 6,800
A8: Adv Gas/Oil Comb Cycle (CC) | B8: 2013 | C8: 400 | D8: 3 | E8: 917 | F8: 1.08 | G8: 1 | H8: 991 | I8: 3.07 | J8: 14.44 | K8: 6,430 | L8: 6,333
A9: Adv CC with carbon sequestration | B9: 2016 | C9: 340 | D9: 3 | E9: 1,813 | F9: 1.08 | G9: 1.04 | H9: 2,036 | I9: 6.37 | J9: 29.89 | K9: 7,525 | L9: 7,493
A10: Conv Comb Turbine8 | B10: 2012 | C10: 85 | D10: 2 | E10: 916 | F10: 1.05 | G10: 1 | H10: 961 | I10: 8.15 | J10: 9.75 | K10: 10,745 | L10: 10,450
A11: Adv Comb Turbine | B11: 2012 | C11: 210 | D11: 2 | E11: 626 | F11: 1.05 | G11: 1 | H11: 658 | I11: 6.9 | J11: 14.52 | K11: 9,750 | L11: 8,550
A12: Fuel Cells | B12: 2013 | C12: 10 | D12: 3 | E12: 5,846 | F12: 1.05 | G12: 1.1 | H12: 6,752 | I12: 0 | J12: 345.8 | K12: 9,500 | L12: 6,960
A13: Adv Nuclear | B13: 2016 | C13: 2236 | D13: 6 | E13: 4,567 | F13: 1.1 | G13: 1.05 | H13: 5,275 | I13: 2 | J13: 87.69 | K13: 10,453 | L13: 10,453
A14: Distributed Generation - Base | B14: 2013 | C14: 2 | D14: 3 | E14: 1,349 | F14: 1.05 | G14: 1 | H14: 1,416 | I14: 7.37 | J14: 16.58 | K14: 9,050 | L14: 8,900
A15: Distributed Generation - Peak | B15: 2012 | C15: 1 | D15: 2 | E15: 1,620 | F15: 1.05 | G15: 1 | H15: 1,701 | I15: 7.37 | J15: 16.58 | K15: 10,069 | L15: 9,880
... A23: Photovoltaic7,10 | B23: 2012 | C23: 150 | D23: 2 | E23: 4,474 | F23: 1.05 | G23: 1 | H23: 4,697 | I23: 0 | J23: 25.73 | K23: 9,854 | L23: 9,854
A24: 1Online year represents the first year that a new unit could be completed, given an order date of 2010. For wind, geothermal and landfill gas, the online year was moved earlier to acknowledge the significant market activity already occuring in anticipation of the expiration of the Production Tax Credit. 2A contingency allowance is defined by the American Association of Cost Engineers as the “specific provision for unforeseeable elements of costs within a defined project scope; particularly important where previous experience has shown that unforeseeable events which will increase costs are likely to occur” 3The technological optimism factor is applied to the first four units of a new, unproven design, it reflects the demonstrated tendency to underestimate actual costs for a first-of-a-kind unit. 4Overnight capital cost including contingency factors, excluding regional multipliers and learning effects. Interest charges are also excluded. These represent costs of new projects initiated in 2010. 5O&M = Operations and maintenance. 6For hydro, wind, and solar technologies, the heatrate shown represents the average heatrate for conventional thermal generation as of 2009. This is used for purposes of calculating primary energy consumption displaced for these resources, and does not imply an estimate of their actual energy conversion efficiency. 7Capital costs are shown before investment tax credits are applied. 8Combustion turbine units can be built by the model prior to 2012 if necessary to meet a given region’s reserve margin. 9Because geothermal and hydro cost and performance characteristics are specific for each site, the table entries represent the cost of the least expensive plant that could be built in the Northwest Power Pool region, where most of the proposed sites are located. 10Costs and capacities are expressed in terms of net AC power available to the grid for the installed capacity. Sources: For the AEO2011 cycle, EIA commissioned an external consultant to develop current cost estimates for utility-scale electric generating plants. This report can be found at http://www.eia.gov/oiaf/beck_plantcosts/index.html. Site specific costs for geothermal were provided by the National Energy Renewable Laboratory, “Updated U.S. Geothermal Supply Curve”, February 2010.

Sheet 2001
A1: Table 43. Cost and Performance Characteristics of New Electricity Generating Technologies
A2: Total Contingency Factors Overnight Cost Overnight including Variable Costs Project Technological contingencies O&M4 Fixed Heatrate in Heatrate in Online Size Leadtimes in 2000 Contingency Optimism in 20003 ($1999 O&M4 2000 2010 Technology Years1 (mW) (Years) ($1999/kW) Factor Factor2 (1999 $/kW) mills/kWh) ($1999/kW) (Btu/kWhr) (Btu/kWhr)
A3: Conventional Pulverized Coal Integrated Coal- Gasification Combined Cycle Conventional Gas/Oil Combined Cycle Adv Gas/Oil Combined Cycle Conv Combustion Turbine5 Adv Combustion Turbine Fuel Cells Advanced Nuclear Generic Distributed Generation6 - Base Generic Distributed Generation6 - Peak Biomass MSW - Landfill Gas Geothermal 7,8 Wind Solar Thermal8 Solar Photovoltaic8 2003 5 2 3,681 1.05 1.10 4,252 0.00 9.85 10,2809 10,2809 1Online year represents the first year that a new unit could be completed, given an order date of 2001. 2The technological optimism factor is applied to the first four units of a new, unproven design, it reflects the demonstrated tendency to underestimate actual costs for a first-of-a-kind unit. 3Overnight capital cost including contingency factors, excluding regional multipliers and learning effects. Interest changes are also excluded. These represent costs of new projects initiated in 2000. 4O&M = Operation and maintenance. 5Combustion turbine units can be built by the model prior to 2003 if necessary to meet a given region’s reserve margin. 6The costs shown here are slightly different from costs shown in Table 45 because of updated adjustments for inflation. The unit size shown here is higher than that shown in Table 45 to reflect the minimum size that can be represented meaningfully in the model. The lead times are also different from those shown in Table 45 because lead times presented here include site acquisition, site preparation, and permitting for plants that are larger in size. 7Because geothermal cost and performance characteristics are specific for each site, the table entries represent the cost of the least expensive plant that could be built in the Northwest Power Pool region, where most of the proposed sites are located. 8Capital costs for geothermal and solar technologies are net of (reduced by) the ten percent investment tax credit. 9Heat rates for solar and wind technologies are fossil-fuel average heat rates.
A5: 2005 | C5: 400 | E5: 4 | F5: 1021 | G5: 1.07 | I5: 1 | J5: 1092 | L5: 3.3 | M5: 22.85 | N5: 9419 | P5: 9087
A6: 2005 | C6: 428 | E6: 4 | F6: 1220 | G6: 1.07 | I6: 1 | J6: 1306 | L6: 0.78 | M6: 31.89 | N6: 7969 | P6: 6968
A7: 2004 | C7: 250 | E7: 3 | F7: 424 | G7: 1.05 | I7: 1 | J7: 445 | L7: 0.51 | M7: 15.24 | N7: 7687 | P7: 7000
A8: 2004 | C8: 400 | E8: 3 | F8: 533 | G8: 1.08 | I8: 1 | J8: 576 | L8: 0.51 | M8: 14.12 | N8: 6927 | P8: 6350
A9: 2003 | C9: 160 | E9: 2 | F9: 315 | G9: 1.05 | I9: 1 | J9: 331 | L9: 0.1 | M9: 6.3 | N9: 11467 | P9: 10600
A10: 2003 | C10: 120 | E10: 2 | F10: 440 | G10: 1.05 | I10: 1 | J10: 462 | L10: 0.1 | M10: 8.94 | N10: 9133 | P10: 8000
A11: 2004 | C11: 10 | E11: 3 | F11: 1767 | G11: 1.05 | I11: 1.1 | J11: 2041 | L11: 2.03 | M11: 14.63 | N11: 5787 | P11: 5361
A12: 2005 | C12: 600 | E12: 4 | F12: 1729 | G12: 1.1 | I12: 1.15 | J12: 2188 | L12: 0.41 | M12: 55.86 | N12: 10400 | P12: 10400
A13: 2004 | C13: 2 | E13: 3 | F13: 579 | G13: 1.05 | I13: 1 | J13: 608 | L13: 14.75 | M13: 3.92 | N13: 10991 | P13: 9210
A14: 2003 | C14: 1 | E14: 2 | F14: 520 | G14: 1.05 | I14: 1 | J14: 546 | L14: 22.55 | M14: 12.26 | N14: 10620 | P14: 10500
A15: 2005 | C15: 100 | E15: 4 | F15: 1464 | G15: 1.07 | I15: 1.1 | J15: 1723 | L15: 2.83 | M15: 43.88 | N15: 8911 | P15: 8911
A16: 2004 | C16: 30 | E16: 3 | F16: 1304 | G16: 1.07 | I16: 1 | J16: 1395 | L16: 0.01 | M16: 94.01 | N16: 13648 | P16: 13648
A17: 2005 | C17: 50 | E17: 4 | F17: 1626 | G17: 1.05 | I17: 1 | J17: 1708 | L17: 0 | M17: 70.69 | N17: 31241 | P17: 30862
A18: 2004 | C18: 50 | E18: 3 | F18: 919 | G18: 1.07 | I18: 1 | J18: 983 | L18: 0 | M18: 26 | N18: 10,2809 | P18: 10,2809
A19: 2004 | C19: 100 | E19: 3 | F19: 2394 | G19: 1.07 | I19: 1.15 | J19: 2946 | L19: 0 | M19: 46.72 | N19: 10,2809 | P19: 10,2809
A20: Source: Values are derived by the Energy Information Administration, Office of Integrated Analysis and Forecasting, from analysis of reports and discussions with various sources from industry, government, and the Department of Energy National Laboratories.
A21: Table 44. Regional Multipliers for Construction of Fossil-Fueled, Nuclear, and Renewable1 Generating Technologies
A22: EMM Region NE, NY MAAC STV MAPP,
H23: ECAR, MAIN | K23: SPP
A24: 1.043 | B24: 0.996 | D24: 0.96 | H24: 1.004 | K24: 0.997
A25: EMM Region RA | B25: NWP | D25: FL | H25: CNV | K25: ERCOT
A26: 1.003 | B26: 1.026 | D26: 0.961 | H26: 1.058 | K26: 0.986
A27: 1Regional multipliers are not applied to geothermal technologies because costs are site specific.
A28: Source: Argonne National Laboratory, Cost and Performance Database for Electric Power Generating Technologies..
A29: Technological Optimism and Learning Overnight costs for each technology are calculated as a function of regional construction parameters, project contingency, and technological optimism and learning factors. For each generating technology available for new capacity in a region, the overnight cost used by the model is calculated using the base cost technological optimism and contingency factors for the technology from Table 43 and the learning parameters from Table 45.

Sheet 2002
A1: Table 38. Cost and Performance Characteristics of New Electricity Generating Technologies
A2: Total Overnight Contingency Factors Cost Overnight including Variable Heatrate Heatrate Costs Contingencies O&M4 Fixed in in Online Size Leadtimes in 2001 in 20013 ($2000 O&M4 2001 2010 Technology Years1 (mW) (Years) ($2000/kW) (2000 $/kW) mills/kWh) ($2000/kW) (Btu/kWhr) (Btu/kWr)
A3: Conventional Pulverized Coal | C3: 2005 | D3: 400 | F3: 4 | G3: 1046 | I3: 1.07 | M3: 1 | O3: 1119 | Q3: 3.38 | S3: 23.41 | T3: 9386 | V3: 9087
A4: Integrated Coal- Gasification Combined | C4: 2005 | D4: 428 | F4: 4 | G4: 1250 | I4: 1.07 | M4: 1 | O4: 1338 | Q4: 0.8 | S4: 32.67 | T4: 7869 | V4: 6968
A5: Cycle Conventional Gas/Oil Combined Cycle | C5: 2004 | D5: 250 | F5: 3 | G5: 435 | I5: 1.05 | M5: 1 | O5: 456 | Q5: 0.52 | S5: 15.61 | T5: 7618 | V5: 7000
A6: Adv Gas/Oil Combined Cycle | C6: 2004 | D6: 400 | F6: 3 | G6: 546 | I6: 1.08 | M6: 1 | O6: 590 | Q6: 0.52 | S6: 14.46 | T6: 6870 | V6: 6350
A7: Conv Combustion Turbine5 | C7: 2002 | D7: 160 | F7: 2 | G7: 323 | I7: 1.05 | M7: 1 | O7: 339 | Q7: 0.1 | S7: 6.45 | T7: 11380 | V7: 10600
A8: Adv Combustion Turbine | C8: 2003 | D8: 120 | F8: 2 | G8: 451 | I8: 1.05 | M8: 1 | O8: 474 | Q8: 0.1 | S8: 9.16 | T8: 9020 | V8: 8000
A9: Fuel Cells | C9: 2004 | D9: 10 | F9: 3 | G9: 1810 | I9: 1.05 | M9: 1.1 | O9: 2091 | Q9: 2.08 | S9: 14.98 | T9: 5744 | V9: 5361
A10: Advanced Nuclear | C10: 2005 | D10: 600 | F10: 4 | G10: 1772 | I10: 1.1 | M10: 1.1 | O10: 2144 | Q10: 0.42 | S10: 57.23 | T10: 10400 | V10: 10400
A11: Generic Distributed Generation6 - Base Generic Distributed Generation6 - Peak
A12: 2004 | H12: 2 | K12: 3 | L12: 593 | N12: 1.05 | P12: 1 | R12: 623 | U12: 15.11 | W12: 4.02 | Y12: 10991 | AA12: 9210
A13: 2003 | H13: 1 | K13: 2 | L13: 533 | N13: 1.05 | P13: 1 | R13: 559 | U13: 23.1 | W13: 12.56 | Y13: 10620 | AA13: 10500
A14: Biomass | B14: 2005 | D14: 100 | F14: 4 | G14: 1536 | J14: 1.07 | M14: 1.05 | O14: 1725 | Q14: 2.9 | S14: 44.95 | T14: 8911 | V14: 8911
A15: MSW - Landfill Gas | B15: 2004 | D15: 30 | F15: 3 | G15: 1336 | J15: 1.07 | M15: 1 | O15: 1429 | Q15: 0.01 | S15: 96.31 | T15: 13648 | V15: 13648
A16: Geothermal 7,8 | B16: 2006 | D16: 50 | F16: 4 | G16: 1663 | J16: 1.05 | M16: 1 | O16: 1746 | Q16: 0 | S16: 70.07 | T16: 32173 | V16: 32173
A17: Wind | B17: 2004 | D17: 50 | F17: 3 | G17: 918 | J17: 1.07 | M17: 1 | O17: 982 | Q17: 0 | S17: 25.54 | T17: 10280 | V17: 10280
A18: Solar Thermal8 | B18: 2004 | D18: 100 | F18: 3 | G18: 2157 | J18: 1.07 | M18: 1.1 | O18: 2539 | Q18: 0 | S18: 47.87 | T18: 10280 | V18: 10280
A19: Solar Photovoltaic8 | B19: 2003 | D19: 5 | F19: 2 | G19: 3317 | J19: 1.05 | M19: 1.1 | O19: 3831 | Q19: 0 | S19: 9.85 | T19: 10280 | V19: 10280
A20: 1Online year represents the first year that a new unit could be completed, given an order date of 2001. 2The technological optimism factor is applied to the first four units of a new, unproven design. It reflects the demonstrated tendency to underestimate actual costs for a first-of-a-kind unit. 3Overnight capital cost including contingency factors, excluding regional multipliers and learning effects. Interest charges are also excluded. These represent costs of new projects initiated in 2001. 4O&M = Operation and maintenance. 5Combustion turbine units can be built by the model prior to 2003 if necessary to meet a given region’s reserve margin. 6The costs shown here are slightly different from costs shown in Table 41 because of updated adjustments for inflation. The unit size shown here is higher than that shown in Table 41 to reflect the minimum size that can be represented meaningfully in the model. The lead times are also different from those shown in Table 41 because lead times presented here include site acquisition, site preparation, and permitting for plants that are larger in size. 7Because geothermal cost and performance characteristics are specific for each site, the table entries represent the cost of the least expensive plant that could be built in the Northwest Power Pool region, where most of the proposed sites are located. 8Capital costs for geothermal and solar technologies are net of (reduced by) the ten percent investment tax credit.
A21: Source: Values are derived by the Energy Information Administration, Office of Integrated Analysis and Forecasting, from analysis of reports and discussions with various sources from industry, government, and the Department of Energy National Laboratories.
A22: Table 39. Regional Multipliers for Construction of Fossil-Fueled, Nuclear, and Renewable1 Generating Technologies
A23: EMM Region NE, NY | E23: MAAC | I23: STV | N23: MAPP, ECAR, MAIN | S23: SPP
A24: 1.043 | E24: 0.996 | I24: 0.96 | N24: 1.004 | S24: 0.997
A25: EMM Region RA | E25: NWP | I25: FL | N25: CNV | S25: ERCOT
A26: 1.003 | E26: 1.026 | I26: 0.961 | N26: 1.058 | S26: 0.986
A27: 1Regional multipliers are not applied to geothermal technologies because costs are site specific.
A28: Source: Argonne National Laboratory, Cost and Performance Database for Electric Power Generating Technologies..
A29: Technological Optimism and Learning Overnight costs for each technology are calculated as a function of regional construction parameters, project contingency, and technological optimism and learning factors. For each generating technology available for new capacity in a region, the overnight cost used by the model is calculated using the base cost, technological optimism and contingency factors for the technology from Table 38, the regional factors from Table 39, and the learning parameters from Table 40.

Sheet 2003
A1: Total Overnight Contingency Factors Cost Overnight including Variable Heatrate Heatrate Costs2 Project Technological Contingencies O&M5 Fixed in nth-of- Online Size Leadtimes in 2002 Contingency Optimism in 20024 ($2001 O&M5 2002 a-kind Technology Years1 (mW) (Years) ($2001/kW) Factor Factor3 (2001 $/kW) mills/kWh) ($2001/kW) (Btu/kWhr) (Btu/kWr)
A2: Scrubbed Coal Newl 2006 | B2: 600 | D2: 4 | E2: 1079 | F2: 1.07 | G2: 1 | H2: 1154 | I2: 3.07 | J2: 24.52 | K2: 9000 | L2: 8600
A3: Integrated Coal- Gasification Combined 2006 | B3: 550 | D3: 4 | E3: 1277 | F3: 1.07 | G3: 1 | H3: 1367 | I3: 2.04 | J3: 33.72 | K3: 8000 | L3: 7200
A4: Cycle
A5: Conventional Gas/Oil 2005 | B5: 250 | D5: 3 | E5: 510 | F5: 1.05 | G5: 1 | H5: 536 | I5: 2.04 | J5: 12.26 | K5: 7500 | L5: 7000
A6: Adv Gas/Oil Combined 2005 | B6: 400 | D6: 3 | E6: 563 | F6: 1.08 | G6: 1 | H6: 608 | I6: 2.04 | J6: 10.22 | K6: 7000 | L6: 6350
A7: Conv Combustion Turbine6 2004 | B7: 160 | D7: 2 | E7: 389 | F7: 1.05 | G7: 1 | H7: 409 | I7: 4.09 | J7: 10.22 | K7: 10939 | L7: 10450
A8: Adv Combustion Turbine 2004 | B8: 230 | D8: 2 | E8: 439 | F8: 1.05 | G8: 1 | H8: 460 | I8: 3.07 | J8: 8.17 | K8: 9394 | L8: 8550
A9: Fuel Cells 2005 | B9: 10 | D9: 3 | E9: 1850 | F9: 1.05 | G9: 1.1 | H9: 2137 | I9: 20.43 | J9: 7.15 | K9: 7500 | L9: 6750
A10: Advanced Nuclear 2007 | B10: 1000 | D10: 5 | E10: 1750 | F10: 1.1 | G10: 1.1 | H10: 2117 | I10: 0.43 | J10: 58.48 | K10: 10400 | L10: 10400
A11: Distributed 2005 | B11: 2 | D11: 3 | E11: 766 | F11: 1.05 | G11: 1 | H11: 804 | I11: 6.13 | J11: 13.79 | K11: 9400 | L11: 8900
A12: Distributed 2004 | B12: 1 | D12: 2 | E12: 919 | F12: 1.05 | G12: 1 | H12: 965 | I12: 6.13 | J12: 13.79 | K12: 10400 | L12: 9880
A13: Biomass 2006 | B13: 100 | D13: 4 | E13: 1569 | F13: 1.07 | G13: 1.05 | H13: 1763 | I13: 2.96 | J13: 45.94 | K13: 8911 | L13: 8911
A14: MSW - Landfill Gas 2005 | B14: 30 | D14: 3 | E14: 1365 | F14: 1.07 | G14: 1 | H14: 1460 | I14: 0.01 | J14: 98.42 | K14: 13648 | L14: 13648
A15: Geothermal 7,8 2006 | B15: 50 | D15: 4 | E15: 1681 | F15: 1.05 | G15: 1 | H15: 1766 | I15: 0 | J15: 71.75 | K15: 32320 | L15: 31797
A16: Wind 2005 | B16: 50 | D16: 3 | E16: 938 | F16: 1.07 | G16: 1 | H16: 1003 | I16: 0 | J16: 26.1 | K16: 10280 | L16: 10280
... A18: Solar Photovoltaic8 2004 | B18: 5 | D18: 2 | E18: 3389 | F18: 1.05 | G18: 1.1 | H18: 3915 | I18: 0 | J18: 10.06 | K18: 10280 | L18: 10280
A19: Combined Cycle
A20: Cycle
A21: Generation - Base
A22: Generation - Peak
A23: 1Online year represents the first year that a new unit could be completed, given an order date of 2002. 2Costs reflect market status and penetration as of 2002. 3The technological optimism factor is applied to the first four units of a new, unproven design. It reflects the demonstrated tendency to underestimate actual costs for a first-of-a-kind unit. 4Overnight capital cost including contingency factors, excluding regional multipliers and learning effects. Interest charges are also excluded. These represent costs of new projects initiated in 2002. 5O&M = Operation and maintenance. 6Combustion turbine units can be built by the model prior to 2004 if necessary to meet a given region’s reserve margin. 7Because geothermal cost and performance characteristics are specific for each site, the table entries represent the cost of the least expensive plant that could be built in the Northwest Power Pool region, where most of the proposed sites are located. 8Capital costs for geothermal and solar technologies are net of (reduced by) the ten percent investment tax credit.
A24: Source: The values shown in this table are developed by the Energy Information Administration, Office of Integrated Analysis and Forecasting, from analysis of reports and discussions with various sources from industry, government, and the Department of Energy Fuel Offices and National Laboratories. They are not based on any specific technology model, but rather, are meant to represent the cost and performance of typical plants under normal operating conditions for each plant type. Key sources reviewed are listed in the ‘Notes and Sources’ section at the end of the chapter.
A25: Table 41. Regional Multipliers for Construction of Fossil-Fueled, Nuclear, and Renewable1 Generating Technologies
A26: EMM Region NE, NY MAAC STV MAPP,
G27: ECAR, MAIN | J27: SPP
A28: 1.043 | C28: 0.996 | E28: 0.96 | G28: 1.004 | J28: 0.997
A29: EMM Region RA | C29: NWP | E29: FL | G29: CNV | J29: ERCOT
A30: 1.003 | C30: 1.026 | E30: 0.961 | G30: 1.058 | J30: 0.986
A31: 1Regional multipliers are not applied to geothermal technologies because costs are site specific.
A32: Source: Argonne National Laboratory, Cost and Performance Database for Electric Power Generating Technologies..
A33: Energy Information Administration/Assumptions to the Annual Energy Outlook 2003 73
A34: Technological Optimism and Learning Overnight costs for each technology are calculated as a function of regional construction parameters, project contingency, and technological optimism and learning factors. For each generating technology available for new capacity in a region, the overnight cost used by the model is calculated using the base cost, technological optimism and contingency factors for the technology from Table 40, the regional factors from Table 41, and the learning parameters from Table 42.

Sheet 2004
A1: Table 38. Cost and Performance Characteristics of New Central Station Electricity Generating Technologies
A2: Base Contingency Factors Total Overnight Overnight Variable Heatrate Heatrate Costs Project Technological Cost O&M5 Fixed in nth-of- Online Size Leadtimes in 2003 Contingency Optimism in 20033 ($2002 O&M5 2003 a-kind Technology Year1 (mW) (Years) ($2002/kW) Factor Factor2 (2002 $/kW) mills/kWh) ($2002/kW) (Btu/kWhr) (Btu/kWr)
A3: Scrubbed Coal New | B3: 2007 | D3: 600 | E3: 4 | G3: 1091 | I3: 1.07 | K3: 1 | N3: 1168 | P3: 3.1 | R3: 24.81 | S3: 9000 | V3: 8600
A4: Integrated Coal- Gasification Combined | B4: 2007 | D4: 550 | E4: 4 | G4: 1292 | I4: 1.07 | K4: 1 | N4: 1383 | P4: 2.07 | R4: 34.11 | S4: 8000 | V4: 7200
A5: Cycle (IGCC)
A6: IGCC with Carbon Sequestration | B6: 2010 | D6: 380 | E6: 4 | G6: 1894 | I6: 1.07 | K6: 1.03 | N6: 2088 | P6: 2.53 | R6: 40.47 | S6: 9600 | V6: 7920
A7: Conv Gas/Oil Comb Cycle | B7: 2006 | D7: 250 | E7: 3 | G7: 516 | I7: 1.05 | K7: 1 | N7: 542 | P7: 2.07 | R7: 12.4 | S7: 7444 | V7: 7000
A8: Adv Gas/Oil Comb Cycle (CC) | B8: 2006 | D8: 400 | E8: 3 | G8: 569 | I8: 1.08 | K8: 1 | N8: 615 | P8: 2.07 | R8: 10.34 | S8: 6928 | V8: 6350
A9: ADV CC with Carbon | B9: 2010 | D9: 400 | E9: 3 | G9: 969 | I9: 1.08 | K9: 1.04 | N9: 1088 | P9: 2.58 | R9: 14.93 | S9: 8646 | V9: 7300
A10: Sequestration
A11: Conv Combustion Turbine5 | F11: 2005 | H11: 160 | J11: 2 | K11: 394 | M11: 1.05 | O11: 1 | Q11: 413 | T11: 4.14 | W11: 10.34 | Y11: 10878 | Z11: 10450
A12: Adv Combustion Turbine | F12: 2005 | H12: 230 | J12: 2 | K12: 444 | M12: 1.05 | O12: 1 | Q12: 466 | T12: 3.1 | W12: 8.27 | Y12: 9289 | Z12: 8550
A13: Fuel Cells | F13: 2006 | H13: 10 | J13: 3 | K13: 1872 | M13: 1.05 | O13: 1.1 | Q13: 2162 | T13: 20.67 | W13: 7.23 | Y13: 7446 | Z13: 6750
A14: Advanced Nuclear | F14: 2013 | H14: 1000 | J14: 6 | K14: 1669 | M14: 1.1 | O14: 1.05 | Q14: 1928 | T14: 0.43 | W14: 59.17 | Y14: 10400 | Z14: 10400
A15: Distributed Generation - | F15: 2006 | H15: 2 | J15: 3 | K15: 775 | M15: 1.05 | O15: 1 | Q15: 813 | T15: 6.2 | W15: 13.95 | Y15: 9400 | Z15: 8900
A16: Base
A17: Peak | AA17: 13.95 | AC17: 10400 | AE17: 9880
A18: Distributed Generation - | C18: 2005 1 2 930 1.05 1.00 977 6.20
A19: Biomass | B19: 2010 | D19: 80 | E19: 4 | G19: 1588 | I19: 1.07 | K19: 1.02 | N19: 1731 | P19: 2.96 | R19: 46.47 | S19: 8911 | U19: 8911
A20: MSW - Landfill Gas | B20: 2006 | D20: 30 | E20: 3 | G20: 1381 | I20: 1.07 | K20: 1 | N20: 1477 | P20: 0.01 | R20: 99.57 | S20: 13648 | U20: 13648
A21: Geothermal 6,7 | B21: 2007 | D21: 50 | E21: 4 | G21: 2099 | I21: 1.05 | K21: 1 | N21: 2203 | P21: 0 | R21: 79.28 | S21: 37259 | U21: 36468
A22: Wind | B22: 2006 | D22: 50 | E22: 3 | G22: 949 | I22: 1.07 | K22: 1 | N22: 1015 | P22: 0 | R22: 26.41 | S22: 10280 | U22: 10280
A23: Solar Thermal7 | B23: 2006 | D23: 100 | E23: 3 | G23: 2478 | I23: 1.07 | K23: 1.1 | N23: 2916 | P23: 0 | R23: 49.48 | S23: 10280 | U23: 10280
A24: Photovoltaic7 | B24: 2005 | D24: 5 | E24: 2 | G24: 3810 | I24: 1.05 | K24: 1.1 | N24: 4401 | P24: 0 | R24: 10.08 | S24: 10280 | U24: 10280
A25: 1Online year represents the first year that a new unit could be completed, given an order date of 2003. 2The technological optimism factor is applied to the first four units of a new, unproven design. It reflects the demonstrated tendency to underestimate actual costs for a first-of-a-kind unit. 3Overnight capital cost including contingency factors, excluding regional multipliers and learning effects. Interest charges are also excluded. These represent costs of new projects initiated in 2003. 4O&M = Operation and maintenance. 5Combustion turbine units can be built by the model prior to 2005 if necessary to meet a given region’s reserve margin. 6Because geothermal cost and performance characteristics are specific for each site, the table entries represent the cost of the least expensive plant that could be built in the Northwest Power Pool region, where most of the proposed sites are located. 7Capital costs for geothermal and solar technologies are shown before the ten percent investment tax credit is applied.
A26: Sources: The values shown in this table are developed by the Energy Information Administration, Office of Integrated Analysis and Forecasting, from analysis of reports and discussions with various sources from industry, government, and the Department of Energy Fuel Offices and National Laboratories. They are not based on any specific technology model, but rather, are meant to represent the cost and performance of typical plants under normal operating conditions for each plant type. Key sources reviewed are listed in the 'Notes and Sources' section at the end of the chapter.

Sheet 2006
A1: Table 38. Cost and Performance Characteristics of New Central Station Electricity Generating Technologies
A2: Base Contingency Factors Total Overnight Overnight Variable Heatrate Heatrate Costs Project Technological Cost O&M5 Fixed in nth-of- Online Size Leadtimes in 2005 Contingency Optimism in 20053 ($2004 O&M5 2005 a-kind Technology Year1 (mW) (Years) ($2004/kW) Factor Factor2 (2004 $/kW) mills/kWh) ($2004/kW) (Btu/kWhr) (Btu/kWr)
A3: Scrubbed Coal New7 Integrated Coal-Gasification | B3: 2009 | C3: 600 | D3: 4 | E3: 1167 | F3: 1.07 | H3: 1 | K3: 1249 | L3: 4.18 | N3: 25.07 | P3: 8844 | R3: 8600
A4: Combined Cycle (IGCC)7 2009 | F4: 550 | G4: 4 | I4: 1349 | J4: 1.07 | M4: 1 | O4: 1443 | Q4: 2.65 | T4: 35.21 | U4: 8309 | V4: 7200
A5: Sequestration | T5: 41.44 | U5: 9713 | V5: 7920
A6: IGCC with Carbon | C6: 2010 380 4 1,873 1.07 1.03 2,065 4.04
A7: Conv Gas/Oil Comb Cycle | B7: 2008 | C7: 250 | D7: 3 | E7: 556 | F7: 1.05 | H7: 1 | K7: 584 | L7: 1.88 | N7: 11.37 | P7: 7196 | R7: 6800
A8: Adv Gas/Oil Comb Cycle (CC) | B8: 2008 | C8: 400 | D8: 3 | E8: 532 | F8: 1.08 | H8: 1 | K8: 575 | L8: 1.82 | N8: 10.65 | P8: 6752 | R8: 6333
A9: ADV CC with Carbon Sequestration | B9: 2010 | C9: 400 | D9: 3 | E9: 1021 | F9: 1.08 | H9: 1.04 | K9: 1147 | L9: 2.68 | N9: 18.12 | P9: 8613 | R9: 7493
A10: Conv Combustion Turbine5 | B10: 2007 | C10: 160 | D10: 2 | E10: 388 | F10: 1.05 | H10: 1 | K10: 407 | L10: 3.25 | N10: 11.03 | P10: 10842 | R10: 10450
A11: Adv Combustion Turbine | B11: 2007 | C11: 230 | D11: 2 | E11: 367 | F11: 1.05 | H11: 1 | K11: 385 | L11: 2.89 | N11: 9.59 | P11: 9227 | R11: 8550
A12: Fuel Cells | B12: 2008 | C12: 10 | D12: 3 | E12: 3787 | F12: 1.05 | H12: 1.1 | K12: 4374 | L12: 43.64 | N12: 5.15 | P12: 7930 | R12: 6960
A13: Advanced Nuclear | B13: 2013 | C13: 1000 | D13: 6 | E13: 1744 | F13: 1.1 | H13: 1.05 | K13: 2014 | L13: 0.45 | N13: 61.82 | P13: 10400 | R13: 10400
A14: Distributed Generation -Base | B14: 2008 | C14: 2 | D14: 3 | E14: 791 | F14: 1.05 | H14: 1 | K14: 831 | L14: 6.49 | N14: 14.6 | P14: 9650 | R14: 8900
A15: Distributed Generation -Peak | B15: 2007 | C15: 1 | D15: 2 | E15: 951 | F15: 1.05 | H15: 1 | K15: 998 | L15: 6.49 | N15: 14.6 | P15: 10823 | R15: 9880
A16: Biomass | B16: 2009 | C16: 80 | D16: 4 | E16: 1659 | F16: 1.07 | H16: 1.02 | K16: 1809 | L16: 3.13 | N16: 48.56 | P16: 8911 | R16: 8911
A17: MSW - Landfill Gas | B17: 2008 | C17: 30 | D17: 3 | E17: 1443 | F17: 1.07 | H17: 1 | K17: 1544 | L17: 0.01 | N17: 104.03 | P17: 13648 | R17: 13648
A18: Geothermal 6,7 | B18: 2009 | C18: 50 | D18: 4 | E18: 2100 | F18: 1.05 | H18: 1 | K18: 2205 | L18: 0 | N18: 75 | P18: 32173 | R18: 35460
... A22: Photovoltaic7 | B22: 2007 | C22: 5 | D22: 2 | E22: 3981 | F22: 1.05 | H22: 1.1 | K22: 4598 | L22: 0 | N22: 10.64 | P22: 10280 | R22: 10280
A23: 1Online year represents the first year that a new unit could be completed, given an order date of 2005. 2The technological optimism factor is applied to the first four units of a new, unproven design, or regulatory structure. It reflects the demonstrated tendency to underestimate actual costs for a first-of-a-kind unit. 3Overnight capital cost including contingency factors, excluding regional multipliers and learning effects. Interest charges are also excluded. These represent costs of new projects initiated in 2005. 4O&M = Operations and maintenance. 5Combustion turbine units can be built by the model prior to 2007 if necessary to meet a given region’s reserve margin. 6Because geothermal and hydro cost and performance characteristics are specific for each site, the table entries represent the cost of the least expensive plant that could be built in the Northwest Power Pool region, where most of the proposed sites are located. 7Capital costs are shown before investment tax credits are applied.
A24: Sources: The values shown in this table are developed by the Energy Information Administration, Office of Integrated Analysis and Forecasting, from analysis of reports and discussions with various sources from industry, government, and the Department of Energy Fuel Offices and National Laboratories. They are not based on any specific technology model, but rather, are meant to represent the cost and performance of typical plants under normal operating conditions for each plant type. Key sources reviewed are listed in the ‘Notes and Sources’ section at the end of the chapter.

Sheet 2008
A1: Table 38. Cost and Performance Characteristics of New Central Station Electricity Generating Technologies
A2: Base Contingency Factors Total Overnight Overnight Variable Heatrate6 Heatrate Cost Project Technological Cost O&M5 Fixed in nth-of- Online Size Leadtime in 2007 Contingency Optimism in 20074 ($2006 O&M5 2007 a-kind Technology Year1 (mW) (Years) ($2006/kW) Factor2 Factor3 (2006 $/kW) mills/kWh) ($2006/kW) (Btu/kWhr) (Btu/kWr)
A3: Scrubbed Coal New7 Integrated Coal-Gasification | C3: 2011 | E3: 600 | F3: 4 | G3: 1434 | I3: 1.07 | K3: 1 | N3: 1534 | O3: 4.46 | Q3: 26.79 | R3: 9200 | T3: 8740
A4: Combined Cycle (IGCC)7 2011 | H4: 550 | J4: 4 | L4: 1657 | M4: 1.07 | P4: 1 | R4: 1773 | S4: 2.84 | U4: 37.62 | V4: 8765 | X4: 7450
A5: Sequestration | U5: 44.27 | V5: 10781 | X5: 8307
A6: IGCC with Carbon | B6: 2011 380 4 2,302 1.07 1.03 2,537 4.32
A7: Conv Gas/Oil Comb Cycle | D7: 2010 | E7: 250 | F7: 3 | G7: 683 | I7: 1.05 | K7: 1 | N7: 717 | O7: 2.01 | Q7: 12.14 | R7: 7196 | T7: 6800
A8: Adv Gas/Oil Comb Cycle (CC) | D8: 2010 | E8: 400 | F8: 3 | G8: 654 | I8: 1.08 | K8: 1 | N8: 706 | O8: 1.95 | Q8: 11.38 | R8: 6752 | T8: 6333
A9: ADV CC with Carbon Sequestration | D9: 2010 | E9: 400 | F9: 3 | G9: 1254 | I9: 1.08 | K9: 1.04 | N9: 1409 | O9: 2.86 | Q9: 19.36 | R9: 8613 | T9: 7493
A10: Conv Combustion Turbine8 | D10: 2009 | E10: 160 | F10: 2 | G10: 476 | I10: 1.05 | K10: 1 | N10: 500 | O10: 3.47 | Q10: 11.78 | R10: 10833 | T10: 10450
A11: Adv Combustion Turbine | D11: 2009 | E11: 230 | F11: 2 | G11: 450 | I11: 1.05 | K11: 1 | N11: 473 | O11: 3.08 | Q11: 10.24 | R11: 9289 | T11: 8550
A12: Fuel Cells | D12: 2010 | E12: 10 | F12: 3 | G12: 4653 | I12: 1.05 | K12: 1.1 | N12: 5374 | O12: 46.62 | Q12: 5.5 | R12: 7930 | T12: 6960
A13: Advanced Nuclear | D13: 2016 | E13: 1350 | F13: 6 | G13: 2143 | I13: 1.1 | K13: 1.05 | N13: 2475 | O13: 0.48 | Q13: 66.05 | R13: 10400 | T13: 10400
A14: Distributed Generation -Base | D14: 2009 | E14: 5 | F14: 2 | G14: 972 | I14: 1.05 | K14: 1 | N14: 1021 | O14: 6.93 | Q14: 15.59 | R14: 9200 | T14: 8900
A15: Distributed Generation -Peak | D15: 2010 | E15: 2 | F15: 3 | G15: 1168 | I15: 1.05 | K15: 1 | N15: 1227 | O15: 6.93 | Q15: 15.59 | R15: 10257 | T15: 9880
A16: Biomass | D16: 2011 | E16: 80 | F16: 4 | G16: 2490 | I16: 1.07 | K16: 1.05 | N16: 2809 | O16: 6.53 | Q16: 62.7 | R16: 8911 | T16: 8911
A17: MSW - Landfill Gas | D17: 2010 | E17: 30 | F17: 3 | G17: 1773 | I17: 1.07 | K17: 1 | N17: 1897 | O17: 0.01 | Q17: 111.15 | R17: 13648 | T17: 13648
A18: Geothermal 7,9 | D18: 2011 | E18: 50 | F18: 4 | G18: 1057 | I18: 1.05 | K18: 1 | N18: 1110 | O18: 0 | Q18: 160.18 | R18: 35376 | T18: 33729
... A23: Photovoltaic7 | D23: 2009 | E23: 5 | F23: 2 | G23: 5380 | I23: 1.05 | K23: 1 | N23: 5649 | O23: 0 | Q23: 11.37 | R23: 10022 | T23: 10022
A24: 1Online year represents the first year that a new unit could be completed, given an order date of 2007. 2A contingency allowance is defined by the American Association of Cost Engineers as the "specific provision for unforeseeable elements if costs within a defined project scope; particularly important where previous experience has shown that unforeseeable events which will increase costs are likely to occur." 3The technological optimism factor is applied to the first four units of a new, unproven design. It reflects the demonstrated tendency to underestimate actual costs for a first-of-a-kind unit. 4Overnight capital cost including contingency factors, excluding regional multipliers and learning effects. Interest charges are also excluded. These represent costs of new projects initiated in 2007. 5O&M = Operations and maintenance. 6For hydro, wind, and solar technologies, the heatrate shown represents the average heatrate for conventional thermal generation as of 2006. This is used for purposes of calculating primary energy consumption displaced for these resources, and does not imply an estimate of their actual energy conversion efficiency. 7Capital costs are shown before investment tax credits are applied. 8Combustion turbine units can be built by the model prior to 2009 if necessary to meet a given region's reserve margin. 9Because geothermal and hydro cost and performance characteristics are specific for each site, the table entries represent the cost of the least expensive plant that could be built in the Northwest Power Pool region, where most of the proposed sites are located.
A25: Sources: The values shown in this table are developed by the Energy Information Administration, Office of Integrated Analysis and Forecasting, from analysis of reports and discussions with various sources from industry, government, and the Department of Energy Fuel Offices and National Laboratories. They are not based on any specific technology model, but rather, are meant to represent the cost and performance of typical plants under normal operating conditions for each plant type. Key sources reviewed are listed in the ‘Notes and Sources’ section at the end of the chapter.

Sheet 2009
A1: Table 8.2. Cost and Performance Characteristics of New Central Station Electricity Generating Technologies
A2: Base Contingency Factors Total Overnight Overnight Variable Heatrate6 Heatrate Cost Project Technological Cost O&M5 Fixed in nth-of- Online Size Leadtime in 2008 Contingency Optimism in 20084 ($2007 O&M5 2008 a-kind Technology Year1 (mW) (Years) ($2007/kW) Factor2 Factor3 (2007 $/kW) mills/kWh) ($2007/kW) (Btu/kWhr) (Btu/kWr)
A3: Scrubbed Coal New7 Integrated Coal-Gasification | B3: 21012 | D3: 600 | E3: 4 | F3: 1923 | H3: 1.07 | I3: 1 | L3: 2058 | O3: 4.59 | P3: 27.53 | R3: 9200 | S3: 8740
A4: Combined Cycle (IGCC)7 2012 | G4: 550 | J4: 4 | K4: 2223 | M4: 1.07 | N4: 1 | Q4: 2378 | S4: 2.92 | U4: 38.67 | W4: 8765 | Y4: 7450
A5: CC with Carbon 2016 | G5: 380 | J5: 4 | K5: 3172 | M5: 1.07 | N5: 1.03 | Q5: 3496 | S5: 4.44 | U5: 46.12 | W5: 10781 | Y5: 8307
A6: IG Sequestration
A7: Conv Gas/Oil Comb Cycle | C7: 2011 | D7: 250 | E7: 3 | F7: 917 | H7: 1.05 | I7: 1 | L7: 962 | O7: 2.07 | P7: 12.48 | R7: 7196 | T7: 6800
A8: Adv Gas/Oil Comb Cycle (CC) | C8: 2011 | D8: 400 | E8: 3 | F8: 877 | H8: 1.08 | I8: 1 | L8: 948 | O8: 2 | P8: 11.7 | R8: 6752 | T8: 6333
A9: ADV CC with Carbon Sequestration | C9: 2016 | D9: 400 | E9: 3 | F9: 1683 | H9: 1.08 | I9: 1.04 | L9: 1890 | O9: 2.94 | P9: 19.9 | R9: 8613 | T9: 7493
A10: Conv Combustion Turbine8 | C10: 2010 | D10: 160 | E10: 2 | F10: 638 | H10: 1.05 | I10: 1 | L10: 670 | O10: 3.57 | P10: 12.11 | R10: 10810 | T10: 10450
A11: Adv Combustion Turbine | C11: 2010 | D11: 230 | E11: 2 | F11: 604 | H11: 1.05 | I11: 1 | L11: 634 | O11: 3.17 | P11: 10.53 | R11: 9289 | T11: 8550
A12: Fuel Cells | C12: 2011 | D12: 10 | E12: 3 | F12: 4640 | H12: 1.05 | I12: 1.1 | L12: 5360 | O12: 47.92 | P12: 5.65 | R12: 7930 | T12: 6960
A13: Advanced Nuclear | C13: 2016 | D13: 1350 | E13: 6 | F13: 2873 | H13: 1.1 | I13: 1.05 | L13: 3318 | O13: 0.49 | P13: 90.02 | R13: 10434 | T13: 10434
A14: Distributed Generation -Base | C14: 2011 | D14: 2 | E14: 3 | F14: 1305 | H14: 1.05 | I14: 1 | L14: 1370 | O14: 7.12 | P14: 16.03 | R14: 9050 | T14: 8900
A15: Distributed Generation -Peak | C15: 2010 | D15: 1 | E15: 2 | F15: 1566 | H15: 1.05 | I15: 1 | L15: 1645 | O15: 7.12 | P15: 16.03 | R15: 10069 | T15: 9880
A16: Biomass | C16: 2012 | D16: 80 | E16: 4 | F16: 3339 | H16: 1.07 | I16: 1.05 | L16: 3766 | O16: 6.71 | P16: 64.45 | R16: 9646 | T16: 7765
A17: MSW - Landfill Gas | C17: 2010 | D17: 30 | E17: 3 | F17: 2377 | H17: 1.07 | I17: 1 | L17: 2543 | O17: 0.01 | P17: 114.25 | R17: 13648 | T17: 13648
A18: Geothermal 7,9 | C18: 2010 | D18: 50 | E18: 4 | F18: 1630 | H18: 1.05 | I18: 1 | L18: 1711 | O18: 0 | P18: 164.64 | R18: 34633 | T18: 30301
... A23: Photovoltaic7 | C23: 2011 | D23: 5 | E23: 2 | F23: 5750 | H23: 1.05 | I23: 1 | L23: 6038 | O23: 0 | P23: 11.68 | R23: 9919 | T23: 9919
A24: 1Online year represents the first year that a new unit could be completed, given an order date of 2008. For wind, geothermal and landfill gas, the online year was moved earlier to acknowledge the significant market activity already occuring in anticipation of the expiration of the Production Tax Credit in 2009 for wind and 2010 for the others. 2A contingency allowance is defined by the American Association of Cost Engineers as the "specific provision for unforeseeable elements if costs within a defined project scope; particularly important where previous experience has shown that unforeseeable events which will increase costs are likely to occur." 3The technological optimism factor is applied to the first four units of a new, unproven design. It reflects the demonstrated tendency to underestimate actual costs for a first-of-a-kind unit. 4Overnight capital cost including contingency factors, excluding regional multipliers and learning effects. Interest charges are also excluded. These represent costs of new projects initiated in 2008. 5O&M = Operations and maintenance. 6For hydro, wind, and solar technologies, the heatrate shown represents the average heatrate for conventional thermal generation as of 2007. This is used for purposes of calculating primary energy consumption displaced for these resources, and does not imply an estimate of their actual energy conversion efficiency. 7Capital costs are shown before investment tax credits are applied. 8Combustion turbine units can be built by the model prior to 2010 if necessary to meet a given region’s reserve margin. 9Because geothermal and hydro cost and performance characteristics are specific for each site, the table entries represent the cost of the least expensive plant that could be built in the Northwest Power Pool region, where most of the proposed sites are located. Sources: The values shown in this table are developed by the Energy Information Administration, Office of Integrated Analysis and Forecasting, from analysis of reports and discussions with various sources from industry, government, and the Department of Energy Fuel Offices and National Laboratories. They are not based on any specific technology model, but rather, are meant to represent the cost and performance of typical plants under normal operating conditions for each plant type. Key sources reviewed are listed in the ‘Notes and Sources’ section at the end of the chapter.

Sheet 2013
A1: Table 8.2. Cost and performance characteristics of new central station electricity generating technologies
A2: Base | F2: Contingency Factors Total | K2: nth-of-a-
D3: Overnight Cost in | E3: Project | F3: Techno- | G3: Overnight Cost in | H3: Variable | I3: Fixed | J3: Heatrate6 | L3: kind
D4: Lead 2012 | E4: Contin- | F4: logical | G4: 20124 | H4: O&M5 | I4: O&M | J4: in 2012 | L4: Heatrate
C5: Online Size | D5: time (2011 $/ | E5: gency | F5: Optimism | G5: (2011 $/ | H5: (2011 $/ | I5: (2011$/ | J5: (Btu/ | L5: (Btu/
A6: Technology | C6: Year1 (mW) | D6: (years) kW) | E6: Factor2 | F6: Factor3 | G6: kW) | H6: mWh) | I6: kW) | J6: kWh) | L6: kWh)
A7: Scrubbed Coal New7 | C7: 2016 1300 | D7: 4 2,694 | E7: 1.07 | F7: 1 | G7: 2883 | H7: 4.39 | I7: 30.64 | J7: 8800 | L7: 8740
A8: Integrated Coal- Gasification Comb Cycle (IGCC)7 | C8: 2016 1200 | D8: 4 3,475 | E8: 1.07 | F8: 1 | G8: 3718 | H8: 7.09 | I8: 50.49 | J8: 8700 | L8: 7450
A9: P C | B9: ulverized Coal with arbon sequestion | C9: 2017 650 | D9: 4 4,662 | E9: 1.07 | F9: 1.03 | G9: 5138 | H9: 4.37 | I9: 65.31 | J9: 12000 | L9: 9316
A10: C C | B10: onv Gas/Oil Comb ycle | C10: 2015 620 | D10: 3 858 | E10: 1.05 | F10: 1 | G10: 901 | H10: 3.54 | I10: 12.94 | J10: 7050 | L10: 6800
A11: Adv Gas/Oil Comb Cycle (CC) | C11: 2015 400 | D11: 3 931 | E11: 1.08 | F11: 1 | G11: 1006 | H11: 3.21 | I11: 15.1 | J11: 6430 | L11: 6333
A12: Adv CC with carbon sequestration | C12: 2017 340 | D12: 3 1,833 | E12: 1.08 | F12: 1.04 | G12: 2059 | H12: 6.66 | I12: 31.23 | J12: 7525 | L12: 7493
A13: C T | B13: onv Comb urbine8 | C13: 2014 85 | D13: 2 910 | E13: 1.05 | F13: 1 | G13: 956 | H13: 15.18 | I13: 7.21 | J13: 10850 | L13: 10450
A14: Adv Comb Turbine | C14: 2014 210 | D14: 2 632 | E14: 1.05 | F14: 1 | G14: 664 | H14: 10.19 | I14: 6.92 | J14: 9750 | L14: 8550
A15: F | B15: uel Cells | C15: 2015 10 | D15: 3 6,045 | E15: 1.05 | F15: 1.1 | G15: 6982 | H15: 0 | I15: 357.47 | J15: 9500 | L15: 6960
A16: Adv Nuclear | C16: 2018 2236 | D16: 6 4,700 | E16: 1.1 | F16: 1.05 | G16: 5429 | H16: 2.1 | I16: 91.65 | J16: 10452 | L16: 10452
A17: Distributed Generation - Base | C17: 2015 2 | D17: 3 1,395 | E17: 1.05 | F17: 1 | G17: 1465 | H17: 7.62 | I17: 17.14 | J17: 9038 | L17: 8900
A18: Distributed Generation - Peak | C18: 2015 1 | D18: 2 1,675 | E18: 1.05 | F18: 1 | G18: 1759 | H18: 7.62 | I18: 17.14 | J18: 10042 | L18: 9880
A19: B | B19: iomass | C19: 2016 50 | D19: 4 3,685 | E19: 1.07 | F19: 1.02 | G19: 4041 | H19: 5.17 | I19: 103.79 | J19: 13500 | L19: 13500
A20: Geothermal7,9 | C20: 2013 50 | D20: 4 2,444 | E20: 1.05 | F20: 1 | G20: 2567 | H20: 0 | I20: 110.94 | J20: 9756 | L20: 9756
A21: MSW - Landfill Gas Hydropower9 | C21: 2013 50 2016 500 | D21: 3 7,858 4 2,179 | E21: 1.07 1.10 | F21: 1.00 1.00 | G21: 8,408 2,397 | H21: 8.51 2.60 | I21: 381.74 14.57 | J21: 13,648 9,756 | L21: 13,648 9,756
A22: Wind | C22: 2013 100 | D22: 3 2,032 | E22: 1.07 | F22: 1 | G22: 2175 | H22: 0 | I22: 38.86 | J22: 9756 | L22: 9756
A23: Wind Offshore | C23: 2016 400 | D23: 4 4,452 | E23: 1.1 | F23: 1.25 | G23: 6121 | H23: 0 | I23: 72.71 | J23: 9756 | L23: 9756
A24: So | B24: lar Thermal7 | C24: 2015 100 | D24: 3 4,653 | E24: 1.07 | F24: 1 | G24: 4979 | H24: 0 | I24: 66.09 | J24: 9756 | L24: 9756
A25: Conventional
A26: Photovoltaic7,10 2014 150 2 3,624 1.05 1.00 3,805 0.00 21.37 9,756 9,756 1Online year represents the first year that a new unit could be completed, given an order date of 2012. For wind, geothermal and landfill gas, the online year was moved earlier to acknowledge the significant market activity already occurring in anticipation of the expiration of the Production Tax Credit. 2A contingency allowance is defined by the American Association of Cost Engineers as the “specific provision for unforeseeable elements of costs within a defined project scope; particularly important where previous experience has shown that unforeseeable events which will increase costs are likely to occur” 3The technological optimism factor is applied to the first four units of a new, unproven design, it reflects the demonstrated tendency to underestimate actual costs for a first-of-a-kind unit. 4 Overnight capital cost including contingency factors, excluding regional multipliers and learning effects. Interest charges are also excluded. These represent costs of new projects initiated in 2012. 5O&M = Operations and maintenance. 6For hydro, wind, solar and geothermal technologies, the heatrate shown represents the average heatrate for conventional thermal generation as of 2011. This is used for purposes of calculating primary energy consumption displaced for these resources, and does not imply an estimate of their actual energy conversion efficiency. 7Capital costs are shown before investment tax credits are applied. 8Combustion turbine units can be built by the model prior to 2014 if necessary to meet a given region’s reserve margin. 9Because geothermal and hydro cost and performance characteristics are specific for each site, the table entries represent the cost of the least expensive plant that could be built in the Northwest Power Pool region, where most of the proposed sites are located. 10Costs and capacities are expressed in terms of net AC power available to the grid for the installed capacity. Sources: For the AEO2013, EIA updated cost estimates for utility-scale electric generating plants, based on a draft report provided by external consultants. The final report can be found at www.eia.gov/forecasts/capitalcost/. Site specific costs for geothermal were provided by the National Energy Renewable Laboratory, “Updated U.S. Geothermal Supply Curve”, February 2010.
A27: Technological optimism and learning Overnight costs for each technology are calculated as a function of regional construction parameters, project contingency, and technological optimism and learning factors. The technological optimism factor represents the demonstrated tendency to underestimate actual costs for a first-of-a-kind, unproven technology. As experience is gained (after building 4 units) the technological optimism factor is gradually reduced to 1.0. The learning function in NEMS is determined at a component level. Each new technology is broken into its major components, and each component is identified as revolutionary, evolutionary or mature. Different learning rates are assumed for each component, based on the level of experience with the design component (Table 8.3). Where technologies use similar components, these components learn at the same rate as these units are built. For example, it is assumed that the underlying turbine generator for a combustion turbine, combined cycle and integrated coal-gasification combined cycle unit is basically the same. Therefore construction of any of these technologies would contribute to learning reductions for the turbine component. The learning function has the nonlinear form: OC(C) = a*C-b, where C is the cumulative capacity for the technology component.

Sheet 2007
A1: Table 39. Cost and Performance Characteristics of New Central Station Electricity Generating Technologies
A2: Base Contingency Factors Total Overnight Overnight Variable Heatrate Heatrate Costs Project Technological Cost O&M5 Fixed in nth-of- Online Size Leadtimes in 2006 Contingency Optimism in 20063 ($2005 O&M5 2006 a-kind Technology Year1 (mW) (Years) ($2005/kW) Factor Factor2 (2005 $/kW) mills/kWh) ($2005/kW) (Btu/kWhr) (Btu/kWr)
A3: Scrubbed Coal New7 Integrated Coal-Gasification | C3: 2010 | E3: 600 | F3: 4 | G3: 1206 | H3: 1.07 | J3: 1 | M3: 1290 | N3: 4.32 | P3: 25.91 | R3: 8844 | T3: 8600
A4: Combined Cycle (IGCC)7 2010 | H4: 550 | I4: 4 | K4: 1394 | L4: 1.07 | N4: 1 | Q4: 1491 | S4: 2.75 | V4: 36.38 | W4: 8309 | Y4: 7200
A5: Sequestration | V5: 42.82 | W5: 9713 | Y5: 7920
A6: IGCC with Carbon | B6: 2010 380 4 1,936 1.07 1.03 2,134 4.18
A7: Conv Gas/Oil Comb Cycle | D7: 2009 | E7: 250 | F7: 3 | G7: 574 | H7: 1.05 | J7: 1 | M7: 603 | N7: 1.94 | O7: 11.75 | R7: 7163 | U7: 6800
A8: Adv Gas/Oil Comb Cycle (CC) | D8: 2009 | E8: 400 | F8: 3 | G8: 550 | H8: 1.08 | J8: 1 | M8: 594 | N8: 1.88 | O8: 11.01 | R8: 6717 | U8: 6333
A9: ADV CC with Carbon Sequestration | D9: 2010 | E9: 400 | F9: 3 | G9: 1055 | H9: 1.08 | J9: 1.04 | M9: 1185 | N9: 2.77 | O9: 18.72 | R9: 8547 | U9: 7493
A10: Conv Combustion Turbine5 | D10: 2008 | E10: 160 | F10: 2 | G10: 400 | H10: 1.05 | J10: 1 | M10: 420 | N10: 3.36 | O10: 11.4 | R10: 10807 | U10: 10450
A11: Adv Combustion Turbine | D11: 2008 | E11: 230 | F11: 2 | G11: 379 | H11: 1.05 | J11: 1 | M11: 398 | N11: 2.98 | O11: 9.91 | R11: 9166 | U11: 8550
A12: Fuel Cells | D12: 2009 | E12: 10 | F12: 3 | G12: 3913 | H12: 1.05 | J12: 1.1 | M12: 4520 | N12: 45.09 | O12: 5.32 | R12: 7873 | U12: 6960
A13: Advanced Nuclear | D13: 2014 | E13: 1350 | F13: 6 | G13: 1802 | H13: 1.1 | J13: 1.05 | M13: 2081 | N13: 0.47 | O13: 63.88 | R13: 10400 | U13: 10400
A14: Distributed Generation -Base | D14: 2009 | E14: 2 | F14: 3 | G14: 818 | H14: 1.05 | J14: 1 | M14: 859 | N14: 6.7 | O14: 15.08 | R14: 9500 | U14: 8900
A15: Distributed Generation -Peak | D15: 2008 | E15: 1 | F15: 2 | G15: 983 | H15: 1.05 | J15: 1 | M15: 1032 | N15: 6.7 | O15: 15.08 | R15: 10634 | U15: 9880
A16: Biomass | D16: 2010 | E16: 80 | F16: 4 | G16: 1714 | H16: 1.07 | J16: 1.02 | M16: 1869 | N16: 2.96 | O16: 50.18 | R16: 8911 | U16: 8911
A17: MSW - Landfill Gas | D17: 2009 | E17: 30 | F17: 3 | G17: 1491 | H17: 1.07 | J17: 1 | M17: 1595 | N17: 0.01 | O17: 107.5 | R17: 13648 | U17: 13648
A18: Geothermal 6,7 | D18: 2010 | E18: 50 | F18: 4 | G18: 1790 | H18: 1.05 | J18: 1 | M18: 1880 | N18: 0 | O18: 154.92 | R18: 36025 | U18: 30641
... A22: Photovoltaic7 | D22: 2008 | E22: 5 | F22: 2 | G22: 4114 | H22: 1.05 | J22: 1.1 | M22: 4751 | N22: 0 | O22: 10.99 | R22: 10280 | U22: 10280
A23: 1Online year represents the first year that a new unit could be completed, given an order date of 2006. 2The technological optimism factor is applied to the first four units of a new, unproven design, or regulatory structure. It reflects the demonstrated tendency to underestimate actual costs for a first-of-a-kind unit. 3Overnight capital cost including contingency factors, excluding regional multipliers and learning effects. Interest charges are also excluded. These represent costs of new projects initiated in 2006. 4O&M = Operations and maintenance. 5Combustion turbine units can be built by the model prior to 2008 if necessary to meet a given region’s reserve margin. 6Because geothermal and hydro cost and performance characteristics are specific for each site, the table entries represent the cost of the least expensive plant that could be built in the Northwest Power Pool region, where most of the proposed sites are located. 7Capital costs are shown before investment tax credits are applied.
A24: Sources: The values shown in this table are developed by the Energy Information Administration, Office of Integrated Analysis and Forecasting, from analysis of reports and discussions with various sources from industry, government, and the Department of Energy Fuel Offices and National Laboratories. They are not based on any specific technology model, but rather, are meant to represent the cost and performance of typical plants under normal operating conditions for each plant type. Key sources reviewed are listed in the ‘Notes and Sources’ section at the end of the chapter.

Sheet 2020
A1: Table 3. Cost and performance characteristics of new central station electricity generating technologies
A2: Technology | B2: First available year1 | C2: Size (MW) | D2: Lead time (years) | E2: Base overnight cost2 (2019 $/kW) | F2: Techno- logical optimism factor3 | G2: Total overnight cost4,5 (2019 $/kW) | H2: Variable O&M6 (2019 $/MWh) | I2: Fixed O&M (2019$/ kW-yr) | J2: Heat rate7 (Btu/kWh)
A3: Ultra-supercritical coal (USC) | B3: 2023 | C3: 650 | D3: 4 | E3: 3661 | F3: 1 | G3: 3661 | H3: 4.48 | I3: 40.41 | J3: 8638
A4: USC with 30% carbon capture and sequestration (CCS) | B4: 2023 | C4: 650 | D4: 4 | E4: 4539 | F4: 1.03 | G4: 4652 | H4: 7.05 | I4: 54.07 | J4: 9751
A5: USC with 90% CCS | B5: 2023 | C5: 650 | D5: 4 | E5: 5851 | F5: 1.03 | G5: 5997 | H5: 10.93 | I5: 59.29 | J5: 12507
A6: Combined-cycle—single shaft | B6: 2022 | C6: 418 | D6: 3 | E6: 1079 | F6: 1 | G6: 1079 | H6: 2.54 | I6: 14.04 | J6: 6431
A7: Combined-cycle—multi shaft | B7: 2022 | C7: 1083 | D7: 3 | E7: 954 | F7: 1 | G7: 954 | H7: 1.86 | I7: 12.15 | J7: 6370
A8: Combined-cycle with 90% CCS | B8: 2022 | C8: 377 | D8: 3 | E8: 2470 | F8: 1.04 | G8: 2569 | H8: 5.82 | I8: 27.48 | J8: 7124
A9: Internal combustion engine | B9: 2021 | C9: 21 | D9: 2 | E9: 1802 | F9: 1 | G9: 1802 | H9: 5.67 | I9: 35.01 | J9: 8295
A10: Combustion turbine— aeroderivative8 | B10: 2021 | C10: 105 | D10: 2 | E10: 1170 | F10: 1 | G10: 1170 | H10: 4.68 | I10: 16.23 | J10: 9124
A11: Combustion turbine—industrial frame | B11: 2021 | C11: 237 | D11: 2 | E11: 710 | F11: 1 | G11: 710 | H11: 4.48 | I11: 6.97 | J11: 9905
A12: Fuel cells | B12: 2022 | C12: 10 | D12: 3 | E12: 6671 | F12: 1.1 | G12: 7339 | H12: 0.59 | I12: 30.65 | J12: 6469
A13: Advanced nuclear | B13: 2025 | C13: 2156 | D13: 6 | E13: 6016 | F13: 1.05 | G13: 6317 | H13: 2.36 | I13: 121.13 | J13: 10461
A14: Distributed generation—base | B14: 2022 | C14: 2 | D14: 3 | E14: 1555 | F14: 1 | G14: 1555 | H14: 8.57 | I14: 19.28 | J14: 8946
A15: Distributed generation—peak | B15: 2021 | C15: 1 | D15: 2 | E15: 1868 | F15: 1 | G15: 1868 | H15: 8.57 | I15: 19.28 | J15: 9934
A16: Battery storage | B16: 2020 | C16: 50 | D16: 1 | E16: 1383 | F16: 1 | G16: 1383 | H16: 0 | I16: 24.7 | J16: NA
A17: Biomass | B17: 2023 | C17: 50 | D17: 4 | E17: 4080 | F17: 1.01 | G17: 4104 | H17: 4.81 | I17: 125.19 | J17: 13500
A18: Geothermal9,10 | B18: 2023 | C18: 50 | D18: 4 | E18: 2680 | F18: 1 | G18: 2680 | H18: 1.16 | I18: 113.29 | J18: 9156
A19: Municipal solid waste—landfill gas | B19: 2022 | C19: 36 | D19: 3 | E19: 1557 | F19: 1 | G19: 1557 | H19: 6.17 | I19: 20.02 | J19: 8513
A20: Conventional hydropower10 | B20: 2023 | C20: 100 | D20: 4 | E20: 2752 | F20: 1 | G20: 2752 | H20: 1.39 | I20: 41.63 | J20: NA
A21: Wind5 | B21: 2022 | C21: 200 | D21: 3 | E21: 1319 | F21: 1 | G21: 1319 | H21: 0 | I21: 26.22 | J21: NA
A22: Wind offshore9 | B22: 2023 | C22: 400 | D22: 4 | E22: 4356 | F22: 1.25 | G22: 5446 | H22: 0 | I22: 109.54 | J22: NA
A23: Solar thermal9 | B23: 2022 | C23: 115 | D23: 3 | E23: 7191 | F23: 1 | G23: 7191 | H23: 0 | I23: 85.03 | J23: NA
A24: Solar photovoltaic —tracking5,9,11 | B24: 2021 | C24: 150 | D24: 2 | E24: 1331 | F24: 1 | G24: 1331 | H24: 0 | I24: 15.19 | J24: NA
A25: 1 Represents the first year that a new unit could become operational. 2 Base cost includes project contingency costs. 3 The technological optimism factor is applied to the first four units of a new, unproven design; it reflects the demonstrated tendency to underestimate actual costs for a first- of-a-kind unit. 4 Overnight capital cost includes contingency factors and excludes regional multipliers (except as noted for wind and solar PV) and learning effects. Interest charges are also excluded. The capital costs represent current costs for plants that would come online in 2020. 5 Wind and solar PV technologies' total overnight cost in the table shows the average input value across all 25 electricity market regions, as weighted by the respective capacity of that type installed during 2018 in each region to account for the substantial regional variation in wind and solar costs (as shown in Table 4). The input value used for onshore wind in AEO2020 was $1,260 per kilowatt (kW) and for solar PV with tracking it was $1,307/kW, which represents the cost of building a plant excluding regional factors. Region-specific factors contributing to the substantial regional variation in cost include differences in typical project size across regions, accessibility of resources, and variation in labor and other construction costs through the country. 6 O&M = Operations and maintenance. 7 The nuclear average heat rate is the weighted average tested heat rate for nuclear units as reported on the Form EIA-860, Annual Electric Generator Report. No heat rate is reported for battery storage because it is not a primary conversion technology; conversion losses are accounted for when the electricity is first generated; electricity-to- storage losses are accounted for through the additional demand for electricity required to meet load. For hydropower, wind, solar, and geothermal technologies, no heat rate is reported because the power is generated without fuel combustion and no set British thermal unit conversion factors exist. The model calculates the average heat rate for fossil generation in each year to report primary energy consumption displaced for these resources. 8 Combustion turbine aeroderivative units can be built by the model before 2021, if necessary, to meet a region's reserve margin. 9 Capital costs are shown before investment tax credits are applied. 10 Because geothermal and hydropower cost and performance characteristics are specific for each site, the table entries show the cost of the least expensive plant that could be built in the Northwest region for hydro and Great Basin region for geothermal, where most of the proposed sites are located. 11 Costs and capacities are expressed in terms of net AC (alternating current) power available to the grid for the installed capacity. Sources: Input costs are primarily based on a report provided by external consultants: Sargent & Lundy, December 2019. Hydropower site costs for non-powered dams were most recently updated for AEO2018 using data from Oak Ridge National Lab

Sheet 2019
A1: Table 2. Cost and performance characteristics of new central station electricity generating technologies
A2: Technology | B2: First available year1 | D2: Size (MW) | E2: Lead time (years) | F2: Base overnight cost (2018 $/kW) | G2: Project contingency factor2 | H2: Techno- logical optimism factor3 | I2: Total overnight cost4,10 (2018 $/kW) | J2: Variable O&M5 (2018 $/MWh) | L2: Fixed O&M (2018$/ kW/yr) | M2: Heat rate6 (Btu/ kWh) | N2: Final heat rate (Btu/kWh)
A3: Coal with 30% carbon sequestration (CCS) | C3: 2022 | D3: 650 | E3: 4 | F3: 4713 | G3: 1.07 | H3: 1.03 | I3: 5169 | J3: 7.31 | L3: 72.12 | M3: 9750 | N3: 9221
A4: Coal with 90% CCS | C4: 2022 | D4: 650 | E4: 4 | F4: 5212 | G4: 1.07 | H4: 1.03 | I4: 5716 | J4: 9.89 | L4: 83.75 | M4: 11650 | N4: 9257
A5: Conv gas/oil combined cycle (CC) | C5: 2021 | D5: 702 | E5: 3 | F5: 952 | G5: 1.05 | H5: 1 | I5: 999 | J5: 3.61 | L5: 11.33 | M5: 6600 | N5: 6350
A6: Adv gas/oil CC | C6: 2021 | D6: 1100 | E6: 3 | F6: 736 | G6: 1.08 | H6: 1 | I6: 794 | J6: 2.06 | L6: 10.3 | M6: 6300 | N6: 6200
A7: Adv CC with CCS | C7: 2021 | D7: 340 | E7: 3 | F7: 1963 | G7: 1.08 | H7: 1.04 | I7: 2205 | J7: 7.34 | L7: 34.43 | M7: 7525 | N7: 7493
A8: Internal combustion engine | C8: 2020 | D8: 85 | E8: 2 | F8: 1306 | G8: 1.05 | H8: 1 | I8: 1371 | J8: 6.03 | L8: 7.11 | M8: 8500 | N8: 8160
A9: Conv combustion turbine7 | C9: 2020 | D9: 100 | E9: 2 | F9: 1072 | G9: 1.05 | H9: 1 | I9: 1126 | J9: 3.61 | L9: 18.03 | M9: 9840 | N9: 9600
A10: Adv combustion turbine | C10: 2020 | D10: 237 | E10: 2 | F10: 658 | G10: 1.05 | H10: 1 | I10: 691 | J10: 11.02 | L10: 7.01 | M10: 9800 | N10: 8550
A11: Fuel cells | C11: 2021 | D11: 10 | E11: 3 | F11: 6250 | G11: 1.05 | H11: 1.1 | I11: 7197 | J11: 46.56 | L11: 0 | M11: 9500 | N11: 6960
A12: Adv nuclear | C12: 2022 | D12: 2234 | E12: 6 | F12: 5224 | G12: 1.1 | H12: 1.05 | I12: 6034 | J12: 2.37 | L12: 103.31 | M12: 10461 | N12: 10461
A13: Distributed generation— base | C13: 2021 | D13: 2 | E13: 3 | F13: 1501 | G13: 1.05 | H13: 1 | I13: 1576 | J13: 8.4 | L13: 18.9 | M13: 8958 | N13: 8900
A14: Distributed generation— peak | C14: 2020 | D14: 1 | E14: 2 | F14: 1804 | G14: 1.05 | H14: 1 | I14: 1894 | J14: 8.4 | L14: 18.9 | M14: 9948 | N14: 9880
A15: Battery storage | C15: 2019 | D15: 30 | E15: 1 | F15: 1857 | G15: 1.05 | H15: 1 | I15: 1950 | J15: 7.26 | L15: 36.32 | M15: NA | N15: NA
A16: Biomass | C16: 2022 | D16: 50 | E16: 4 | F16: 3642 | G16: 1.07 | H16: 1 | I16: 3900 | J16: 5.7 | L16: 114.39 | M16: 13500 | N16: 13500
A17: Geothermal8,9 | C17: 2022 | D17: 50 | E17: 4 | F17: 2654 | G17: 1.05 | H17: 1 | I17: 2787 | J17: 0 | L17: 122.28 | M17: NA | N17: NA
A18: MSW—landfill gas | C18: 2021 | D18: 50 | E18: 3 | F18: 8313 | G18: 1.07 | H18: 1 | I18: 8895 | J18: 9.47 | L18: 425.38 | M18: 18000 | N18: 18000
A19: Conventional hydropower9 | C19: 2022 | D19: 500 | E19: 4 | F19: 2680 | G19: 1.1 | H19: 1 | I19: 2948 | J19: 1.36 | L19: 40.85 | M19: NA | N19: NA
A20: Wind10 | C20: 2021 | D20: 100 | E20: 3 | F20: 1518 | G20: 1.07 | H20: 1 | I20: 1624 | J20: 0 | L20: 48.42 | M20: NA | N20: NA
A21: Wind offshore8 | C21: 2022 | D21: 400 | E21: 4 | F21: 4758 | G21: 1.1 | H21: 1.25 | I21: 6542 | J21: 0 | L21: 80.14 | M21: NA | N21: NA
A22: Solar thermal8 | C22: 2021 | D22: 100 | E22: 3 | F22: 4011 | G22: 1.07 | H22: 1 | I22: 4291 | J22: 0 | L22: 72.84 | M22: NA | N22: NA
A23: Solar PV— tracking8,10,11 | C23: 2020 | D23: 150 | E23: 2 | F23: 1876 | G23: 1.05 | H23: 1 | I23: 1969 | J23: 0 | L23: 22.46 | M23: NA | N23: NA
A24: Solar PV—fixed tilt8,10,11 | C24: 2020 | D24: 150 | E24: 2 | F24: 1698 | G24: 1.05 | H24: 1 | I24: 1783 | J24: 0 | L24: 22.46 | M24: NA | N24: NA
A25: 1 Represents the first year that a new unit could become operational.
A26: 2 AACE International (the Association for the Advancement of Cost Engineering) has defined contingency as “…an amount added to an estimate to allow for items, conditions, or events for which the state, occurrence, or effect is uncertain and that experience shows will likely result, in aggregate, in additional costs.”
A27: 3 The technological optimism factor is applied to the first four units of a new, unproven design; it reflects the demonstrated tendency to underestimate actual costs for a first-of-a-kind unit.
A28: 4 Overnight capital cost includes contingency factors and excludes regional multipliers (except as noted for wind and solar PV) and learning effects. Interest charges are also excluded. The capital costs represent current costs for plants that would come online in 2019.
A29: 5 O&M = operations and maintenance.
A30: 6 The nuclear average heat rate is the weighted average tested heat rate for nuclear units as reported on the Form EIA-860, Annual Electric Generator Report. No heat rate is reported for battery storage because it is not a primary conversion technology; conversion losses are accounted for when the electricity is first generated; electricity-to-storage losses are accounted for through the additional demand for electricity required to meet load. For hydropower, wind, solar, and geothermal technologies, no heat rate is reported because the power is generated without fuel combustion and no set British thermal unit (Btu) conversion factors exist. The model calculates the average heat rate for fossil generation in each year for reporting primary energy consumption displaced for these resources.
A31: 7 Conventional combustion turbine units can be built by the model before 2020, if necessary, to meet a region's reserve margin.
A32: 8 Capital costs are shown before investment tax credits are applied.
A33: 9 Because geothermal and hydropower cost and performance characteristics are specific for each site, the table entries represent the cost of the least expensive plant that could be built in the Northwest Power Pool region, where most of the proposed sites are located.
A34: 10 Wind and both solar PV technologies' total overnight costs shown in the table show the average input value across all 22 electricity market regions, as weighted by the respective capacity of that type installed during 2017 in each region, to account for the substantial regional variation in wind and solar costs (as shown in Table 3). The input value used for wind in AEO2019 was $1,920 per kilowatt (kW), for solar PV with tracking it was $2,160/kW, and for solar PV fixed tilt it was $2,024, representing the cost of building a plant excluding regional factors. Region-specific factors contributing to the substantial regional variation in cost include differences in typical project size across regions, accessibility of resources, and variation in labor and other construction costs throughout the country.
A35: 11 Costs and capacities are expressed in terms of net alternating current (AC) power available to the grid for the installed capacity. MW = megawatt, kW = kilowatt, MWh = megawatthour, kWh = kilowatthour
A36: Sources: Input costs other than Advanced Combined Cycle are consistent with those used in AEO2018, and they are primarily based on a report provided by external consultants. The base costs above reflect calculated learning cost reductions based on recent builds that occurred since the cost report was provided. The cost differential between the two PV technologies was based on Lawrence Berkeley National Lab's Utility-Scale Solar Report. Hydropower site costs for non-powered dams were updated for AEO2018 using data from Oak Ridge National Lab. Costs for advanced CC were updated for AEO2019 based on a PJM Interconnection Cost of New Entry report and EIA analysis of reported costs.

Sheet 2018
A1: Table 2. Cost and performance characteristics of new central station electricity generating technologies
A2: Technology | B2: First available year1 | C2: Size (MW) | D2: Lead time (years) | E2: Base overnight cost (2017 $/kW) | F2: Project Contin- gency Factor2 | G2: Techno- logical Optimism Factor3 | H2: Total overnight cost4,10 (2017 $/kW) | I2: Variable O&M5 (2017 $/MWh) | J2: Fixed O&M (2017$/ kW/yr) | K2: Heat rate6 (Btu/kWh) | L2: nth-of-a- kind heat rate (Btu/kWh)
A3: Coal with 30% carbon sequestration (CCS) | B3: 2021 | C3: 650 | D3: 4 | E3: 4641 | F3: 1.07 | G3: 1.03 | H3: 5089 | I3: 7.17 | J3: 70.7 | K3: 9750 | L3: 9221
A4: Coal with 90% CCS | B4: 2021 | C4: 650 | D4: 4 | E4: 5132 | F4: 1.07 | G4: 1.03 | H4: 5628 | I4: 9.7 | J4: 82.1 | K4: 11650 | L4: 9257
A5: Conv Gas/Oil Combined Cycle (CC) | B5: 2020 | C5: 702 | D5: 3 | E5: 935 | F5: 1.05 | G5: 1 | H5: 982 | I5: 3.54 | J5: 11.11 | K5: 6600 | L5: 6350
A6: Adv Gas/Oil CC | B6: 2020 | C6: 429 | D6: 3 | E6: 1026 | F6: 1.08 | G6: 1 | H6: 1108 | I6: 2.02 | J6: 10.1 | K6: 6300 | L6: 6200
A7: Adv CC with CCS | B7: 2020 | C7: 340 | D7: 3 | E7: 1936 | F7: 1.08 | G7: 1.04 | H7: 2175 | I7: 7.2 | J7: 33.75 | K7: 7525 | L7: 7493
A8: Conv Combustion Turbine7 | B8: 2019 | C8: 100 | D8: 2 | E8: 1054 | F8: 1.05 | G8: 1 | H8: 1107 | I8: 3.54 | J8: 17.67 | K8: 9880 | L8: 9600
A9: Adv Combustion Turbine | B9: 2019 | C9: 237 | D9: 2 | E9: 648 | F9: 1.05 | G9: 1 | H9: 680 | I9: 10.81 | J9: 6.87 | K9: 9800 | L9: 8550
A10: Fuel Cells | B10: 2020 | C10: 10 | D10: 3 | E10: 6192 | F10: 1.05 | G10: 1.1 | H10: 7132 | I10: 45.64 | J10: 0 | K10: 9500 | L10: 6960
A11: Adv Nuclear | B11: 2022 | C11: 2234 | D11: 6 | E11: 5148 | F11: 1.1 | G11: 1.05 | H11: 5946 | I11: 2.32 | J11: 101.28 | K11: 10460 | L11: 10460
A12: Distributed Generation - Base | B12: 2020 | C12: 2 | D12: 3 | E12: 1479 | F12: 1.05 | G12: 1 | H12: 1553 | I12: 8.23 | J12: 18.52 | K12: 8969 | L12: 8900
A13: Distributed Generation - Peak | B13: 2019 | C13: 1 | D13: 2 | E13: 1777 | F13: 1.05 | G13: 1 | H13: 1866 | I13: 8.23 | J13: 18.52 | K13: 9961 | L13: 9880
A14: Battery Storage | B14: 2018 | C14: 30 | D14: 1 | E14: 2067 | F14: 1.05 | G14: 1 | H14: 2170 | I14: 7.12 | J14: 35.6 | K14: N/A | L14: N/A
A15: Biomass | B15: 2021 | C15: 50 | D15: 4 | E15: 3584 | F15: 1.07 | G15: 1 | H15: 3837 | I15: 5.58 | J15: 112.15 | K15: 13500 | L15: 13500
A16: Geothermal8,9 | B16: 2021 | C16: 50 | D16: 4 | E16: 2615 | F16: 1.05 | G16: 1 | H16: 2746 | I16: 0 | J16: 119.87 | K16: 9271 | L16: 9271
A17: MSW - Landfill Gas | B17: 2020 | C17: 50 | D17: 3 | E17: 8170 | F17: 1.07 | G17: 1 | H17: 8742 | I17: 9.29 | J17: 417.02 | K17: 18000 | L17: 18000
A18: Conventional Hydropower9 | B18: 2021 | C18: 500 | D18: 4 | E18: 2634 | F18: 1.1 | G18: 1 | H18: 2898 | I18: 1.33 | J18: 40.05 | K18: 9271 | L18: 9271
A19: Wind | B19: 2020 | C19: 100 | D19: 3 | E19: 1548 | F19: 1.07 | G19: 1 | H19: 1657 | I19: 0 | J19: 47.47 | K19: 9271 | L19: 9271
A20: Wind Offshore8 | B20: 2021 | C20: 400 | D20: 4 | E20: 4694 | F20: 1.1 | G20: 1.25 | H20: 6454 | I20: 0 | J20: 78.56 | K20: 9271 | L20: 9271
A21: Solar Thermal8 | B21: 2020 | C21: 100 | D21: 3 | E21: 3952 | F21: 1.07 | G21: 1 | H21: 4228 | I21: 0 | J21: 71.41 | K21: 9271 | L21: 9271
A22: Solar PV - tracking8,11 | B22: 2019 | C22: 150 | D22: 2 | E22: 2004 | F22: 1.05 | G22: 1 | H22: 2105 | I22: 0 | J22: 22.02 | K22: 9271 | L22: 9271
A23: Solar PV - fixed tilt8,11 | B23: 2019 | C23: 150 | D23: 2 | E23: 1763 | F23: 1.05 | G23: 1 | H23: 1851 | I23: 0 | J23: 22.02 | K23: 9271 | L23: 9271
A24: 1 - Represents the first year that a new unit could become operational.
A25: 2 - AACE International, the Association for the Advancement of Cost Engineering, has defined contingency as "An amount added to an estimate to allow for items, conditions, or events for which the state, occurrence, or effect is uncertain and that experience shows will likely result, in aggregate, in additional costs.”
A26: 3 - The technological optimism factor is applied to the first four units of a new, unproven design and reflects the demonstrated tendency to underestimate actual costs for a first-of-a-kind unit.
A27: 4 - Overnight capital cost including contingency factors, excluding regional multipliers (except as noted for wind and solar PV) and learning effects. Interest charges are also excluded. These represent current costs for plants that would come online in 2018.
A28: 5 - O&M = Operations and maintenance.
A29: 6 - For hydropower, wind, solar and geothermal technologies, the heat rate shown represents the average heat rate for conventional thermal generation as of 2016. This heat rate is used for purposes of calculating primary energy consumption displaced for these resources, and does not imply an estimate of their actual energy conversion efficiency. The nuclear average heat rate is the weighted average tested heat rate for nuclear units as reported on the Form EIA-860, "Annual Electric Generator Report." No heat rate is reported for battery storage because it is not a primary conversion technology; conversion losses are accounted for when the electricity is first generated; electricity-to-storage losses are accounted for through the additional demand for electricity required to meet load.
A30: 7 - Conventional combustion turbine units can be built by the model prior to 2019 if necessary to meet a given region's reserve margin.
A31: 8 - Capital costs are shown before investment tax credits are applied.
A32: 9 - Because geothermal and hydropower cost and performance characteristics are specific for each site, the table entries represent the cost of the least expensive plant that could be built in the Northwest Power Pool region, where most of the proposed sites are located.
A33: 10 - Wind and both solar PV technologies' total overnight cost shown in the table represents the average input value across all 22 electricity market regions, as weighted by the respective capacity of that type installed during 2016 in each region to account for the substantial regional variation in wind and solar costs (as shown in Table 3). The input value used for wind in AEO2018 was $1,887 per kilowatt (kW), for solar PV with tracking was $2,207/kW, and for solar PV fixed tilt was $2,068, representing the cost of building a plant excluding regional factors. Region-specific factors contributing to the substantial regional variation in cost include differences in typical project size across regions, accessibility of resources, and variation in labor and other construction costs through the country.
A34: 11 - Costs and capacities are expressed in terms of net AC power available to the grid for the installed capacity.
A35: Sources: Input costs are consistent with those used in AEO2017, and are primarily based on a report provided by external consultants, http://www.eia.gov/analysis/studies/powerplants/capitalcost/. The base costs above reflect calculated learning cost reductions based on recent builds occurring since the cost report was provided. The cost differential between the two PV technologies was based on Lawrence Berkeley National Lab's Utility-Scale Solar Report. Hydropower site costs for non-powered dams were updated for AEO2018 using data from Oak Ridge National Lab.

Sheet 2017
A1: Cost and performance characteristics
A2: Table 8.2. of new central station electricity generating technologies
A3: Technology | B3: First available year1 | C3: Size (MW) | D3: Lead time (years) | F3: Base overnight cost in 2016 (2016 $/kW) | G3: Project Contin- gency Factor2 | H3: Techno- logical Optimism Factor3 | I3: Total overnight cost in 20164,10 (2016 $/kW) | J3: Variable O&M5 (2016 $/MWh) | K3: Fixed O&M (2016$/ kW/yr) | L3: Heat rate6 in 2016 (Btu/kWh) | M3: nth-of-a- kind heat rate (Btu/kWh)
A4: Coal with 30% CCS | B4: 2020 | C4: 650 | D4: 4 | F4: 4586 | G4: 1.07 | H4: 1.03 | I4: 5030 | J4: 7.06 | K4: 69.56 | L4: 9750 | M4: 9221
A5: Coal with 90% CCS | B5: 2020 | C5: 650 | D5: 4 | F5: 5072 | G5: 1.07 | H5: 1.03 | I5: 5562 | J5: 9.54 | K5: 80.78 | L5: 11650 | M5: 9257
A6: Conv Gas/Oil Combined Cycle | B6: 2019 | C6: 702 | D6: 3 | F6: 923 | G6: 1.05 | H6: 1 | I6: 969 | J6: 3.48 | K6: 10.93 | L6: 6600 | M6: 6350
A7: Adv Gas/Oil Combined Cycle (CC) | B7: 2019 | C7: 429 | D7: 3 | F7: 1013 | G7: 1.08 | H7: 1 | I7: 1094 | J7: 1.99 | K7: 9.94 | L7: 6300 | M7: 6200
A8: Adv CC with CCS | B8: 2019 | C8: 340 | D8: 3 | F8: 1917 | G8: 1.08 | H8: 1.04 | I8: 2153 | J8: 7.08 | K8: 33.21 | L8: 7525 | M8: 7493
A9: Conv Combustion Turbine7 | B9: 2018 | C9: 100 | D9: 2 | F9: 1040 | G9: 1.05 | H9: 1 | I9: 1092 | J9: 3.48 | K9: 17.39 | L9: 9920 | M9: 9600
A10: Adv Combustion Turbine | B10: 2018 | C10: 237 | D10: 2 | F10: 640 | G10: 1.05 | H10: 1 | I10: 672 | J10: 10.63 | K10: 6.76 | L10: 9800 | M10: 8550
A11: Fuel Cells | B11: 2019 | C11: 10 | D11: 3 | F11: 6252 | G11: 1.05 | H11: 1.1 | I11: 7221 | J11: 44.91 | K11: 0 | L11: 9500 | M11: 6960
A12: Adv Nuclear | B12: 2022 | C12: 2234 | D12: 6 | F12: 5091 | G12: 1.1 | H12: 1.05 | I12: 5880 | J12: 2.29 | K12: 99.65 | L12: 10459 | M12: 10459
A13: Distributed Generation - Base | B13: 2019 | C13: 2 | D13: 3 | F13: 1463 | G13: 1.05 | H13: 1 | I13: 1536 | J13: 8.1 | K13: 18.23 | L13: 8981 | M13: 8900
A14: Distributed Generation - Peak | B14: 2018 | C14: 1 | D14: 2 | F14: 1757 | G14: 1.05 | H14: 1 | I14: 1845 | J14: 8.1 | K14: 18.23 | L14: 9975 | M14: 9880
A15: Biomass | B15: 2020 | C15: 50 | D15: 4 | F15: 3540 | G15: 1.07 | H15: 1 | I15: 3790 | J15: 5.49 | K15: 110.34 | L15: 13500 | M15: 13500
... A24: Solar PV8,10,11 | B24: 2018 | C24: 150 | D24: 2 | F24: 2169 | G24: 1.05 | H24: 1 | I24: 2277 | J24: 0 | K24: 21.66 | L24: 9510 | M24: 9510
A25: 1 - Represents the first year that a new unit could become operational.
A26: 2 - AACE International, the Association for the Advancement of Cost Engineering, has defined contingency as "An amount added to an estimate to allow for items, conditions, or events for which the state, occurrence, or effect is uncertain and that experience shows will likely result, in aggregate, in additional costs.”
A27: 3 - The technological optimism factor is applied to the first four units of a new, unproven design, it reflects the demonstrated tendency to underestimate actual costs for a first-of-a-kind unit.
A28: 4 - Overnight capital cost including contingency factors, excluding regional multipliers (except as noted for wind and solar PV) and learning effects. Interest charges are also excluded. These represent costs of new projects initiated in 2016.
A29: 5 - O&M = Operations and maintenance.
A30: 6 - For hydropower, wind, solar and geothermal technologies, the heat rate shown represents the average heat rate for conventional thermal generation as of 2014. This is used for purposes of calculating primary energy consumption displaced for these resources, and does not imply an estimate of their actual energy conversion efficiency. The nuclear average heat rate is the weighted average tested heat rate for nuclear units as reported on the Form EIA-860, "Annual Electric Generator Report."
A31: 7 – Conventional combustion turbine units can be built by the model prior to 2018 if necessary to meet a given region's reserve margin.
A32: 8 - Capital costs are shown before investment tax credits are applied.
A33: 9 - Because geothermal and hydropower cost and performance characteristics are specific for each site, the table entries represent the cost of the least expensive plant that could be built in the Northwest Power Pool region, where most of the proposed sites are located.
A34: 10 - Wind and solar PV's total overnight cost shown in the table represents the average input value across all 22 electricity market regions, as weighted by the respective capacity of that type installed during 2015 in each region to account for the substantial regional variation in wind and solar costs (as shown in Table 8.3). The input value used for wind in AEO2017 was $1861/kW and for solar PV was $2388/kW, representing the cost of building a plant excluding regional factors. Region-specific factors contributing to the substantial regional variation in cost include differences in typical project size across regions, accessibility of resources, and variation in labor and other construction costs through the country.
A35: 11 - Costs and capacities are expressed in terms of net AC power available to the grid for the installed capacity.
A36: Sources: Costs are consistent with those used in AEO2016, and are primarily based on a report provided by external consultants, which can be found here: http://www.eia.gov/analysis/studies/powerplants/capitalcost/.

Sheet 2016
A1: Table 8.2. Cost and performance characteristics of new central station electricity generating technologies
A2: Contingency Factors
B3: First | D3: Lead | E3: Base Overnight | F3: Project Contin- | G3: Techno- logical | H3: Total Overnight Cost in | I3: Variable O&M5 | J3: Fixed O&M | K3: Heatrate6 | L3: nth-of-a- kind Heatrate
B4: Available | C4: Size | D4: time | E4: Cost in 2015 | F4: gency | G4: Optimism | H4: 20154,10 (2015 | I4: 2015 | J4: (2015 $/ | K4: in 2015 | L4: (Btu/
A5: Technology | B5: Year1 | C5: (MW) | D5: (years) | E5: (2015 $/kW) | F5: Factor2 | G5: Factor3 | H5: $/kW) | I5: $/MWh) | J5: kW/yr.) | K5: (Btu/ kWh) | L5: kWh)
A6: Coal with 30% carbon sequestration (CCS) | B6: 2019 | C6: 650 | D6: 4 | E6: 4649 | F6: 1.07 | G6: 1.03 | H6: 5098 | I6: 6.95 | J6: 68.49 | K6: 9750 | L6: 9221
A7: Conv Gas/Oil Comb Cycle | B7: 2018 | C7: 702 | D7: 3 | E7: 911 | F7: 1.05 | G7: 1 | H7: 956 | I7: 3.42 | J7: 10.76 | K7: 6600 | L7: 6350
A8: Adv Gas/Oil Comb Cycle (CC) | B8: 2018 | C8: 429 | D8: 3 | E8: 1000 | F8: 1.08 | G8: 1 | H8: 1080 | I8: 1.96 | J8: 9.78 | K8: 6300 | L8: 6200
A9: Adv CC with CCS | B9: 2018 | C9: 340 | D9: 3 | E9: 1898 | F9: 1.08 | G9: 1.04 | H9: 2132 | I9: 6.97 | J9: 32.69 | K9: 7525 | L9: 7493
A10: Conv Comb Turbine7 | B10: 2017 | C10: 100 | D10: 2 | E10: 1026 | F10: 1.05 | G10: 1 | H10: 1077 | I10: 3.42 | J10: 17.12 | K10: 9960 | L10: 9600
A11: Adv Comb Turbine | B11: 2017 | C11: 237 | D11: 2 | E11: 632 | F11: 1.05 | G11: 1 | H11: 664 | I11: 10.47 | J11: 6.65 | K11: 9800 | L11: 8550
A12: Fuel Cells | B12: 2018 | C12: 10 | D12: 3 | E12: 6217 | F12: 1.05 | G12: 1.1 | H12: 7181 | I12: 44.21 | J12: 0 | K12: 9500 | L12: 6960
A13: Adv Nuclear | B13: 2022 | C13: 2234 | D13: 6 | E13: 5288 | F13: 1.1 | G13: 1.05 | H13: 6108 | I13: 2.25 | J13: 98.11 | K13: 10449 | L13: 10449
A14: Distributed Generation-Base | B14: 2018 | C14: 2 | D14: 3 | E14: 1448 | F14: 1.05 | G14: 1 | H14: 1520 | I14: 7.98 | J14: 17.94 | K14: 9004 | L14: 8900
A15: Distributed Generation - Peak | B15: 2017 | C15: 1 | D15: 2 | E15: 1739 | F15: 1.05 | G15: 1 | H15: 1826 | I15: 7.98 | J15: 17.94 | K15: 10002 | L15: 9880
A16: Biomass | B16: 2019 | C16: 50 | D16: 4 | E16: 3498 | F16: 1.07 | G16: 1.01 | H16: 3765 | I16: 5.41 | J16: 108.63 | K16: 13500 | L16: 13500
A17: Geothermal8,9 | B17: 2019 | C17: 50 | D17: 4 | E17: 2559 | F17: 1.05 | G17: 1 | H17: 2687 | I17: 0 | J17: 116.12 | K17: 9541 | L17: 9541
... A23: Photovoltaic8,11 | B23: 2017 | C23: 150 | D23: 2 | E23: 2362 | F23: 1.05 | G23: 1 | H23: 2480 | I23: 0 | J23: 21.33 | K23: 9541 | L23: 9541
A24: 1Represents the first year that a new unit could become operational. 2A contingency allowance is defined by the American Association of Cost Engineers as the “specific provision for unforeseeable elements of costs within a defined project scope; particularly important where previous experience has shown that unforeseeable events which will increase costs are likely to occur.” 3The technological optimism factor is applied to the first four units of a new, unproven design; it reflects the demonstrated tendency to underestimate actual costs for a first-of-a-kind unit. 4Overnight capital cost including contingency factors, excluding regional multipliers and learning effects. Interest charges are also excluded. These represent costs of new projects initiated in 2015. 5O&M = Operations and maintenance. 6For hydro, wind, solar and geothermal technologies, the heat rate shown represents the average heat rate for conventional thermal generation as of 2014. This is used for purposes of calculating primary energy consumption displaced for these resources, and does not imply an estimate of their actual energy conversion efficiency. 7 Combustion turbine units can be built by the model prior to 2017 if necessary to meet a given region's reserve margin. 8Capital costs are shown before investment tax credits are applied. 9Because geothermal and hydro cost and performance characteristics are specific for each site, the table entries represent the cost of the least expensive plant that could be built in the Northwest Power Pool region, where most of the proposed sites are located. 10Wind's total overnight cost of $1644/kW represents the average input value across all 22 electricity market regions, as weighted by the wind capacity installed during 2014 in each region to account for the substantial regional variation in wind costs (as shown in Table 8.3). The input value used for AEO 2016 was $1837/kW, and represents the cost of building a 100 MW wind plant excluding regional factors. Region-specific factors contributing to the substantial regional variation in cost include differences in typical project size across regions, accessibility of resources, and variation in labor and other construction costs throughout the country. 11Costs and capacities are expressed in terms of net AC power available to the grid for the installed capacity. Sources: For the AEO2016 cycle, EIA updated cost estimates for certain electric generating technologies, based on a draft report provided by external consultants. This report will be provided on the EIA website when finalized. Costs were updated for coal with CCS, the combined cycle (without CCS) technologies, the combustion turbine technologies, advanced nuclear, onshore wind and solar PV. Costs for other technologies are consistent with AEO2015 assumptions.

Sheet 2015
A1: Table 8.2. Cost and performance characteristics of new central station electricity generating technologies
A2: Contingency Factors
E3: Base | L3: nth-of-
E4: Overnight | F4: Project | G4: Techno- | H4: Total | I4: Variable | J4: Fixed | K4: Heatrate6 | L4: a-kind
D5: Lead | E5: Cost in | F5: Contin- | G5: logical | H5: Overnight | I5: O&M5 | J5: O&M | K5: in 2014 | L5: Heatrate
B6: Online | C6: Size | D6: time | E6: 2014 | F6: gency | G6: Optimism | H6: Cost in 20144 | I6: (2013 $/ | J6: (2013 $/ | K6: (Btu/ | L6: (Btu/
A7: Technology | B7: Year1 | C7: (MW) | D7: (years) | E7: (2013 $/kW) | F7: Factor2 | G7: Factor3 | H7: (2013 $/kW) | I7: mWh) | J7: kW/yr.) | K7: kWh) | L7: kWh
A8: Scrubbed Coal New | B8: 2018 | C8: 1300 | D8: 4 | E8: 2726 | F8: 1.07 | G8: 1 | H8: 2917 | I8: 4.47 | J8: 31.16 | K8: 8800 | L8: 8740
A9: Integrated Coal- Gasifi-
A10: fication Comb
A11: Cycle (IGCC) | B11: 2018 | C11: 1200 | D11: 4 | E11: 3483 | F11: 1.07 | G11: 1 | H11: 3727 | I11: 7.22 | J11: 51.37 | K11: 8700 | L11: 7450
A12: IGCC with Carbon
A13: sequestion | B13: 2018 | C13: 520 | D13: 4 | E13: 5891 | F13: 1.07 | G13: 1.03 | H13: 6492 | I13: 8.44 | J13: 72.8 | K13: 10700 | L13: 8307
A14: Conv Gas/Oil Comb Cycle | B14: 2017 | C14: 620 | D14: 3 | E14: 869 | F14: 1.05 | G14: 1 | H14: 912 | I14: 3.6 | J14: 13.16 | K14: 7050 | L14: 6800
A15: Adv Gas/Oil Comb Cycle
A16: (CC) | B16: 2017 | C16: 400 | D16: 3 | E16: 942 | F16: 1.08 | G16: 1 | H16: 1017 | I16: 3.27 | J16: 15.36 | K16: 6430 | L16: 6333
A17: Adv CC with carbon
A18: sequestration | B18: 2017 | C18: 340 | D18: 3 | E18: 1845 | F18: 1.08 | G18: 1.04 | H18: 2072 | I18: 6.78 | J18: 31.77 | K18: 7525 | L18: 7493
A19: Conv Comb Turbine8 | B19: 2016 | C19: 85 | D19: 2 | E19: 922 | F19: 1.05 | G19: 1 | H19: 968 | I19: 15.44 | J19: 7.34 | K19: 10783 | L19: 10450
A20: Adv Comb Turbine | B20: 2016 | C20: 210 | D20: 2 | E20: 639 | F20: 1.05 | G20: 1 | H20: 671 | I20: 10.37 | J20: 7.04 | K20: 9750 | L20: 8550
A21: Fuel Cells | B21: 2017 | C21: 10 | D21: 3 | E21: 6042 | F21: 1.05 | G21: 1.1 | H21: 6978 | I21: 42.97 | J21: 0 | K21: 9500 | L21: 6960
A22: Adv Nuclear | B22: 2022 | C22: 2234 | D22: 6 | E22: 4646 | F22: 1.1 | G22: 1.05 | H22: 5366 | I22: 2.14 | J22: 93.23 | K22: 10479 | L22: 10479
A23: Distributed
A24: Generation - Base | B24: 2017 | C24: 2 | D24: 3 | E24: 1407 | F24: 1.05 | G24: 1 | H24: 1477 | I24: 7.75 | J24: 17.44 | K24: 9015 | L24: 8900
A25: Distributed
A26: Generation - Peak | B26: 2016 | C26: 1 | D26: 2 | E26: 1689 | F26: 1.05 | G26: 1 | H26: 1774 | I26: 7.75 | J26: 17.44 | K26: 10015 | L26: 9880
A27: Biomass | B27: 2018 | C27: 50 | D27: 4 | E27: 3399 | F27: 1.07 | G27: 1.01 | H27: 3659 | I27: 5.26 | J27: 105.58 | K27: 13500 | L27: 13500
A28: Geothermal7,9 | B28: 2018 | C28: 50 | D28: 4 | E28: 2331 | F28: 1.05 | G28: 1 | H28: 2448 | I28: 0 | J28: 112.85 | K28: 9516 | L28: 9516
A29: Muncipal Solid Waste | B29: 2017 | C29: 50 | D29: 3 | E29: 7730 | F29: 1.07 | G29: 1 | H29: 8271 | I29: 8.74 | J29: 392.6 | K29: 14878 | L29: 18000
A30: Conventional
A31: Hydropower9 | B31: 2018 | C31: 500 | D31: 4 | E31: 2410 | F31: 1.1 | G31: 1 | H31: 2651 | I31: 5.76 | J31: 15.15 | K31: 9516 | L31: 9516
A32: Wind | B32: 2017 | C32: 100 | D32: 3 | E32: 1850 | F32: 1.07 | G32: 1 | H32: 1980 | I32: 0 | J32: 39.53 | K32: 9516 | L32: 9516
A33: Wind Offshore | B33: 2018 | C33: 400 | D33: 4 | E33: 4476 | F33: 1.1 | G33: 1.25 | H33: 6154 | I33: 0 | J33: 73.96 | K33: 9516 | L33: 9516
A34: Solar Thermal7 | B34: 2017 | C34: 100 | D34: 3 | E34: 3787 | F34: 1.07 | G34: 1 | H34: 4052 | I34: 0 | J34: 67.23 | K34: 9516 | L34: 9516
A35: Photovoltaic7,10 | B35: 2016 | C35: 150 | D35: 2 | E35: 3123 | F35: 1.05 | G35: 1 | H35: 3279 | I35: 0 | J35: 24.68 | K35: 9516 | L35: 9516
A36: 1Online year represents the first year that a new unit could be completed, given an order date of 2014. 2A contingency allowance is defined by the American Association of Cost Engineers as the “specific provision for unforeseeable elements of costs within a defined project scope; particularly important where previous experience has shown that unforeseeable events which will increase costs are likely to occur.” 3The technological optimism factor is applied to the first four units of a new, unproven design; it reflects the demonstrated tendency to underestimate actual costs for a first-of-a-kind unit. 4Overnight capital cost including contingency factors, excluding regional multipliers and learning effects. Interest charges are also excluded. These represent costs of new projects initiated in 2014. 5O&M = Operations and maintenance. 6For hydropower, wind, solar and geothermal technologies, the heat rate shown represents the average heat rate for conventional thermal generation as of 2013. This is used for purposes of calculating primary energy consumption displaced for these resources, and does not imply an estimate of their actual energy conversion efficiency. 7Capital costs are shown before investment tax credits are applied. 8Combustion turbine units can be built by the model prior to 2016 if necessary to meet a given region’s reserve margin. 9Because geothermal and hydropower cost and performance characteristics are specific for each site, the table entries represent the cost of the least expensive plant that could be built in the Northwest Power Pool region, where most of the proposed sites are located. 10Costs and capacities are expressed in terms of net AC power available to the grid for the installed capacity. Sources: For the AEO2015 cycle, EIA continues to use the previously developed cost estimates for utility-scale electric generating plants, updated by external consultants for AEO2013. This report can be found at http://www.eia.gov/forecasts/capitalcost/. The costs were assumed to be consistent with plants that would be ordered in 2012, and learning from capacity built in 2012 and 2013 has been applied in the initial costs above. Wind capital costs were updated for AEO2015 using recent reports from trade press and reports from Lawrence Berkeley National Laboratory. Site-specific costs for geothermal were provided by the National Renewable Energy Laboratory, "Updated U.S. Geothermal Supply Curve,” February 2010.

Sheet 2014
A1: Table 8.2. Cost and performance characteristics of new central station electricity generating technologies
A2: Base | F2: Contingency Factors | K2: nth-of-
A3: Technology | B3: Online Year1 | C3: Size (MW) | D3: Lead time (years) | E3: Overnight Cost in 2013 (2012 $/kW) | G3: Project Contin- gency Factor2 | H3: Techno- logical Optimism Factor3 | I3: Total Overnight Cost in 20134 (2012 $/kW) | J3: Variable O&M5 (2012 $/ mWh) | L3: Fixed O&M (2012$/ kW/yr.) | M3: Heatrate6 in 2013 (Btu/ kWh) | N3: a-kind Heatrate (Btu/ kWh
A4: Scrubbed Coal New | B4: 2017 | C4: 1300 | D4: 4 | E4: 2734 | G4: 1.07 | H4: 1 | I4: 2925 | J4: 4.47 | L4: 31.18 | M4: 8800 | N4: 8740
A5: Integrated Coal- Gasification Comb Cycle (IGCC) | B5: 2017 | C5: 1200 | D5: 4 | E5: 3525 | G5: 1.07 | H5: 1 | I5: 3771 | J5: 7.22 | L5: 51.39 | M5: 8700 | N5: 7450
A6: IGCC with Carbon sequestion | B6: 2017 | C6: 520 | D6: 4 | E6: 5958 | G6: 1.07 | H6: 1.03 | I6: 6567 | J6: 8.45 | L6: 72.84 | M6: 10700 | N6: 8307
A7: Conv Gas/Oil Comb Cycle | B7: 2016 | C7: 620 | D7: 3 | E7: 871 | G7: 1.05 | H7: 1 | I7: 915 | J7: 3.6 | L7: 13.17 | M7: 7050 | N7: 6800
A8: Adv Gas/Oil Comb Cycle (CC) | B8: 2016 | C8: 400 | D8: 3 | E8: 945 | G8: 1.08 | H8: 1 | I8: 1021 | J8: 3.27 | L8: 15.37 | M8: 6430 | N8: 6333
A9: Adv CC with carbon sequestration | B9: 2017 | C9: 340 | D9: 3 | E9: 1856 | G9: 1.08 | H9: 1.04 | I9: 2084 | J9: 6.78 | L9: 31.79 | M9: 7525 | N9: 7493
A10: Conv Comb Turbine8 | B10: 2015 | C10: 85 | D10: 2 | E10: 924 | G10: 1.05 | H10: 1 | I10: 971 | J10: 15.45 | L10: 7.34 | M10: 10817 | N10: 10450
A11: Adv Comb Turbine | B11: 2015 | C11: 210 | D11: 2 | E11: 641 | G11: 1.05 | H11: 1 | I11: 673 | J11: 10.37 | L11: 7.04 | M11: 9750 | N11: 8550
A12: Fuel Cells | B12: 2016 | C12: 10 | D12: 3 | E12: 6099 | G12: 1.05 | H12: 1.1 | I12: 7044 | J12: 42.99 | L12: 0 | M12: 9500 | N12: 6960
A13: Adv Nuclear | B13: 2019 | C13: 2234 | D13: 6 | E13: 4763 | G13: 1.1 | H13: 1.05 | I13: 5501 | J13: 2.14 | L13: 93.28 | M13: 10464 | N13: 10464
A14: Distributed Generation - Base | B14: 2016 | C14: 2 | D14: 3 | E14: 1414 | G14: 1.05 | H14: 1 | I14: 1485 | J14: 7.76 | L14: 17.45 | M14: 9027 | N14: 8900
A15: Distributed Generation - Peak | B15: 2015 | C15: 1 | D15: 2 | E15: 1698 | G15: 1.05 | H15: 1 | I15: 1783 | J15: 7.76 | L15: 17.45 | M15: 10029 | N15: 9880
... A22: Solar Thermal7 | B22: 2016 | C22: 100 | D22: 3 | E22: 4715 | G22: 1.07 | H22: 1 | I22: 5045 | J22: 0 | L22: 67.26 | M22: 9716 | N22: 9716
A23: Photovoltaic7,10 | B23: 2015 150 | D23: 2 | E23: 3394 | G23: 1.05 | H23: 1 | I23: 3564 | J23: 0 | L23: 24.69 | M23: 9716 | N23: 9716
A24: 1 Online year represents the first year that a new unit could be completed, given an order date of 2013. For wind, geothermal and landfill gas, the online year was moved earlier to acknowledge both market activity already occurring as well as the incentive for certain types of projects to develop at an accelerated rate in order to qualify for the Production Tax Credit. 2A contingency allowance is defined by the American Association of Cost Engineers as the “specific provision for unforeseeable elements of costs within a defined project scope; particularly important where previous experience has shown that unforeseeable events which will increase costs are likely to occur.” 3The technological optimism factor is applied to the first four units of a new, unproven design; it reflects the demonstrated tendency to underestimate actual costs for a first-of-a-kind unit. 4Overnight capital cost including contingency factors, excluding regional multipliers and learning effects. Interest charges are also excluded. These represent costs of new projects initiated in 2013. 5O&M = Operations and maintenance. 6For hydro, wind, solar and geothermal technologies, the heatrate shown represents the average heatrate for conventional thermal generation as of 2012. This is used for purposes of calculating primary energy consumption displaced for these resources, and does not imply an estimate of their actual energy conversion efficiency. 7Capital costs are shown before investment tax credits are applied. 8Combustion turbine units can be built by the model prior to 2015 if necessary to meet a given region’s reserve margin. 9Because geothermal and hydro cost and performance characteristics are specific for each site, the table entries represent the cost of the least expensive plant that could be built in the Northwest Power Pool region, where most of the proposed sites are located. 10Costs and capacities are expressed in terms of net AC power available to the grid for the installed capacity. Sources: For the AEO2014 cycle, EIA continues to use the previously developed cost estimates for utility-scale electric generating plants, updated by external consultants for AEO2013. This report can be found at http://www.eia.gov/forecasts/capitalcost/. The costs were assumed to be consistent with plants that would be ordered in 2012, and learning from capacity built in 2012 has been applied in the initial costs above. Site-specific costs for geothermal were provided by the National Renewable Energy Laboratory, “Updated U.S. Geothermal Supply Curve,” February 2010.

Sheet 2012
A1: Table 8.2. Cost and performance characteristics of new central station electricity generating technologies
E2: Base Overnight Cost in 2010 (2010 $/ kW) | F2: Contingency Factors | H2: Total Overnight Cost in 20104 (2010 $/ kW) | L2: nth-of-a- kind Heatrate (Btu/ KWh)
A3: Technology | B3: Online Year1 | C3: Size (mW) | D3: Lead time (years) | F3: Project Contin- gency Factor2 | G3: Techno- logical Optimism Factor3 | I3: Variable O&M5 (2010 $/ mWh) | J3: Fixed O&M (2010$/ kW) | K3: Heatrate6 in 2011 (Btu/ KWh)
A4: Scrubbed Coal New7 | B4: 2015 | C4: 1300 | D4: 4 | E4: 2,658 | F4: 1.07 | G4: 1 | H4: 2,844 | I4: 4.25 | J4: 29.67 | K4: 8,800 | L4: 8,740
A5: Integrated Coal- Gasification Comb Cycle (IGCC)7 | B5: 2015 | C5: 1200 | D5: 4 | E5: 3,010 | F5: 1.07 | G5: 1 | H5: 3,220 | I5: 6.87 | J5: 48.9 | K5: 8,700 | L5: 7,450
A6: IGCC with carbon sequestration | B6: 2017 | C6: 520 | D6: 4 | E6: 4,852 | F6: 1.07 | G6: 1.03 | H6: 5,348 | I6: 8.04 | J6: 69.3 | K6: 10,700 | L6: 8,307
A7: Conv Gas/Oil Comb Cycle | B7: 2014 | C7: 540 | D7: 3 | E7: 931 | F7: 1.05 | G7: 1 | H7: 977 | I7: 3.43 | J7: 14.39 | K7: 7,050 | L7: 6,800
A8: Adv Gas/Oil Comb Cycle (CC) | B8: 2014 | C8: 400 | D8: 3 | E8: 929 | F8: 1.08 | G8: 1 | H8: 1,003 | I8: 3.11 | J8: 14.62 | K8: 6,430 | L8: 6,333
A9: Adv CC with carbon sequestration | B9: 2017 | C9: 340 | D9: 3 | E9: 1,834 | F9: 1.08 | G9: 1.04 | H9: 2,060 | I9: 6.45 | J9: 30.25 | K9: 7,525 | L9: 7,493
A10: Conv Comb Turbine8 | B10: 2013 | C10: 85 | D10: 2 | E10: 927 | F10: 1.05 | G10: 1 | H10: 974 | I10: 14.7 | J10: 6.98 | K10: 10,745 | L10: 10,450
A11: Adv Comb Turbine | B11: 2013 | C11: 210 | D11: 2 | E11: 634 | F11: 1.05 | G11: 1 | H11: 666 | I11: 9.87 | J11: 6.7 | K11: 9,750 | L11: 8,550
A12: Fuel Cells | B12: 2014 | C12: 10 | D12: 3 | E12: 5,918 | F12: 1.05 | G12: 1.1 | H12: 6,836 | I12: 0 | J12: 350 | K12: 9,500 | L12: 6,960
A13: Adv Nuclear | B13: 2017 | C13: 2236 | D13: 6 | E13: 4,619 | F13: 1.1 | G13: 1.05 | H13: 5,335 | I13: 2.04 | J13: 88.75 | K13: 10,460 | L13: 10,460
A14: Distributed Generation - Base | B14: 2014 | C14: 2 | D14: 3 | E14: 1,366 | F14: 1.05 | G14: 1 | H14: 1,434 | I14: 7.46 | J14: 16.78 | K14: 9,050 | L14: 8,900
A15: Distributed Generation - Peak | B15: 2013 | C15: 1 | D15: 2 | E15: 1,640 | F15: 1.05 | G15: 1 | H15: 1,722 | I15: 7.46 | J15: 16.78 | K15: 10,056 | L15: 9,880
... A23: Photovoltaic7,10 | B23: 2013 | C23: 150 | D23: 2 | E23: 4,528 | F23: 1.05 | G23: 1 | H23: 4,755 | I23: 0 | J23: 16.7 | K23: 9,760 | L23: 9,760
A24: 1Online year represents the first year that a new unit could be completed, given an order date of 2011. For wind, geothermal and landfill gas, the online year was moved earlier to acknowledge the significant market activity already occuring in anticipation of the expiration of the Production Tax Credit. 2A contingency allowance is defined by the American Association of Cost Engineers as the “specific provision for unforeseeable elements of costs within a defined project scope; particularly important where previous experience has shown that unforeseeable events which will increase costs are likely to occur.” 3The technological optimism factor is applied to the first four units of a new, unproven design; it reflects the demonstrated tendency to underestimate actual costs for a first-of-a-kind unit. 4Overnight capital cost including contingency factors, excluding regional multipliers and learning etfects. Interest charges are also excluded. These represent costs of new projects initiated in 2011. 5O&M = Operations and maintenance. 6For hydro, geothermal, wind, and solar technologies, the heatrate shown represents the average heatrate for conventional thermal generation as of 2010. This is used for purposes of calculating primary energy consumption displaced for these resources, and does not imply an estimate of their actual energy conversion efficiency. 7Capital costs are shown before investment tax credits are applied. 8Combustion turbine units can be built by the model prior to 2013 if necessary to meet a given region’s reserve margin. 9Because geothermal and hydro cost and performance characteristics are specific for each site, the table entries represent the cost of the least expensive plant that could be built in the Northwest Power Pool region, where most of the proposed sites are located. 10Costs and capacities are expressed in terms of net AC power available to the grid for the installed capacity. Sources: For the AEO2012 cycle, EIA continues to use the previously developed cost estimates for utility-scale electric generating plants, prepared by external consultants for AEO2011. This report can be found at www.eia.gov/oiaf/beck_plantcosts/index.html. Site-specific costs for geothermal were provided by the National Energy Renewable Laboratory, “Updated U.S. Geothermal Supply Curve,” February 2010.

Sheet 2010
A1: Table 8.2. Cost and Performance Characteristics of New Central Station Electricity Generating Technologies
A2: Base Contingency Factors Total Overnight Overnight Variable Heatrate6 Heatrate Cost Project Technological Cost O&M5 Fixed in nth-of- Online Size Leadtime in 2009 Contingency Optimism in 20094 ($2008 O&M5 2009 a-kind Technology Year1 (mW) (Years) ($2008/kW) Factor2 Factor3 (2008 $/kW) mills/kWh) ($2008/kW) (Btu/kWhr) (Btu/kWr)
A3: Scrubbed Coal New7 | B3: 2013 | C3: 600 | D3: 4 | E3: 2078 | F3: 1.07 | G3: 1 | H3: 2223 | I3: 4.69 | J3: 28.15 | K3: 9200 | L3: 8740
A4: Integrated Coal-Gasification
A5: Combined Cycle (IGCC)7 | B5: 2013 | C5: 550 | D5: 4 | E5: 2401 | F5: 1.07 | G5: 1 | H5: 2569 | I5: 2.99 | J5: 39.53 | K5: 8765 | L5: 7450
A6: IGCC withCarbon Sequestration | B6: 2016 | C6: 380 | D6: 4 | E6: 3427 | F6: 1.07 | G6: 1.03 | H6: 3776 | I6: 4.54 | J6: 47.15 | K6: 10781 | L6: 8307
A7: Conv Gas/Oil Comb Cycle | B7: 2012 | C7: 250 | D7: 3 | E7: 937 | F7: 1.05 | G7: 1 | H7: 984 | I7: 2.11 | J7: 12.76 | K7: 7196 | L7: 6800
A8: Adv Gas/Oil Comb Cycle (CC) | B8: 2012 | C8: 400 | D8: 3 | E8: 897 | F8: 1.08 | G8: 1 | H8: 968 | I8: 2.04 | J8: 11.96 | K8: 6752 | L8: 6333
A9: ADVCC with Carbon Sequestion | B9: 2016 | C9: 400 | D9: 3 | E9: 1720 | F9: 1.08 | G9: 1.04 | H9: 1932 | I9: 3.01 | J9: 20.35 | K9: 8613 | L9: 7493
A10: Conv Combustion Turbine8 | B10: 2011 | C10: 160 | D10: 2 | E10: 653 | F10: 1.05 | G10: 1 | H10: 685 | I10: 3.65 | J10: 12.38 | K10: 10788 | L10: 10450
A11: Adv Combustion Turbine | B11: 2011 | C11: 230 | D11: 2 | E11: 617 | F11: 1.05 | G11: 1 | H11: 648 | I11: 3.24 | J11: 10.77 | K11: 9289 | L11: 8550
A12: Fuel Cells | B12: 2012 | C12: 10 | D12: 3 | E12: 4744 | F12: 1.05 | G12: 1.1 | H12: 5478 | I12: 49 | J12: 5.78 | K12: 7930 | L12: 6960
A13: Advanced Nuclear | B13: 2016 | C13: 1350 | D13: 6 | E13: 3308 | F13: 1.1 | G13: 1.05 | H13: 3820 | I13: 0.51 | J13: 92.04 | K13: 10488 | L13: 10488
A14: Distributed Generation -Base | B14: 2012 | C14: 2 | D14: 3 | E14: 1334 | F14: 1.05 | G14: 1 | H14: 1400 | I14: 7.28 | J14: 16.39 | K14: 9050 | L14: 8900
A15: Distributed Generation -Peak | B15: 2011 | C15: 1 | D15: 2 | E15: 1601 | F15: 1.05 | G15: 1 | H15: 1681 | I15: 7.28 | J15: 16.39 | K15: 10069 | L15: 9880
A16: Biomass | B16: 2013 | C16: 80 | D16: 4 | E16: 3414 | F16: 1.07 | G16: 1.05 | H16: 3849 | I16: 6.86 | J16: 65.89 | K16: 9451 | L16: 7765
... A23: Photovoltaic7 | B23: 2011 | C23: 5 | D23: 2 | E23: 5879 | F23: 1.05 | G23: 1 | H23: 6171 | I23: 0 | J23: 11.94 | K23: 9884 | L23: 9884
A24: 1Online year represents the first year that a new unit could be completed, given an order date of 2009. For wind, geothermal and landfill gas, the online year was moved earlier to acknowledge the significant market activity already occuring in anticipation of the expiration of the Production Tax Credit. 2A contingency allowance is defined by the American Association of Cost Engineers as the "specific provision for unforeseeable elements if costs within a defined project scope; particularly important where previous experience has shown that unforeseeable events which will increase costs are likely to occur." 3The technological optimism factor is applied to the first four units of a new, unproven design. It reflects the demonstrated tendency to underestimate actual costs for a first-of-a-kind unit. 4Overnight capital cost including contingency factors, excluding regional multipliers and learning effects. Interest charges are also excluded. These represent costs of new projects initiated in 2009. 5O&M = Operations and maintenance. 6For hydro, wind, and solar technologies, the heatrate shown represents the average heatrate for conventional thermal generation as of 2008. This is used for purposes of calculating primary energy consumption displaced for these resources, and does not imply an estimate of their actual energy conversion efficiency. 7Capital costs are shown before investment tax credits are applied. 8Combustion turbine units can be built by the model prior to 2011 if necessary to meet a given region's reserve margin. 9Because geothermal and hydro cost and performance characteristics are specific for each site, the table entries represent the cost of the least expensive plant that could be built in the Northwest Power Pool region, where most of the proposed sites are located.

Sheet 2005
A1: Table 38. Cost and Performance Characteristics of New Central Station Electricity Generating Technologies
A2: Base Contingency Factors Total Overnight Overnight Variable Heatrate Heatrate Costs Project Technological Cost O&M5 Fixed in nth-of- Online Size Leadtimes in 2004 Contingency Optimism in 20043 ($2003 O&M5 2004 a-kind Technology Year1 (mW) (Years) ($2003/kW) Factor Factor2 (2003 $/kW) mills/kWh) ($2003/kW) (Btu/kWhr) (Btu/kWr)
A3: Scrubbed Coal New | B3: 2008 | C3: 600 | D3: 4 | E3: 1134 | F3: 1.07 | G3: 1 | H3: 1213 | I3: 4.06 | J3: 24.36 | K3: 8844 | L3: 8600
A4: Integrated Coal-Gasification
A5: Combined Cycle (IGCC) 2008 | C5: 550 | D5: 4 | E5: 1310 | F5: 1.07 | G5: 1 | H5: 1402 | I5: 2.58 | J5: 34.21 | K5: 8309 | L5: 7200
A6: IGCC with Carbon Sequestration | B6: 2010 | C6: 380 | D6: 4 | E6: 1820 | F6: 1.07 | G6: 1.03 | H6: 2006 | I6: 3.93 | J6: 40.26 | K6: 9713 | L6: 7920
A7: Conv Gas/Oil Comb Cycle | B7: 2007 | C7: 250 | D7: 3 | E7: 540 | F7: 1.05 | G7: 1 | H7: 567 | I7: 1.83 | J7: 11.04 | K7: 7196 | L7: 6800
A8: Adv Gas/Oil Comb Cycle (CC) | B8: 2007 | C8: 400 | D8: 3 | E8: 517 | F8: 1.08 | G8: 1 | H8: 558 | I8: 1.77 | J8: 10.35 | K8: 6752 | L8: 6333
A9: ADV CC with Carbon Sequestration | B9: 2010 | C9: 400 | D9: 3 | E9: 992 | F9: 1.08 | G9: 1.04 | H9: 1114 | I9: 2.6 | J9: 17.6 | K9: 8613 | L9: 7493
A10: Conv Combustion Turbine5 | B10: 2006 | C10: 160 | D10: 2 | E10: 376 | F10: 1.05 | G10: 1 | H10: 395 | I10: 3.16 | J10: 10.72 | K10: 10817 | L10: 10450
A11: Adv Combustion Turbine | B11: 2006 | C11: 230 | D11: 2 | E11: 356 | F11: 1.05 | G11: 1 | H11: 374 | I11: 2.8 | J11: 9.31 | K11: 9183 | L11: 8550
A12: Fuel Cells | B12: 2007 | C12: 10 | D12: 3 | E12: 3679 | F12: 1.05 | G12: 1.1 | H12: 4250 | I12: 42.4 | J12: 5 | K12: 7930 | L12: 6960
A13: Advanced Nuclear | B13: 2013 | C13: 1000 | D13: 6 | E13: 1694 | F13: 1.1 | G13: 1.05 | H13: 1957 | I13: 0.44 | J13: 60.06 | K13: 10400 | L13: 10400
A14: Distributed Generation -Base | B14: 2007 | C14: 2 | D14: 3 | E14: 769 | F14: 1.05 | G14: 1 | H14: 807 | I14: 6.3 | J14: 14.18 | K14: 9950 | L14: 8900
A15: Distributed Generation -Peak | B15: 2006 | C15: 1 | D15: 2 | E15: 924 | F15: 1.05 | G15: 1 | H15: 970 | I15: 6.3 | J15: 14.18 | K15: 11200 | L15: 9880
A16: Biomass | B16: 2008 | C16: 80 | D16: 4 | E16: 1612 | F16: 1.07 | G16: 1.02 | H16: 1757 | I16: 2.96 | J16: 47.18 | K16: 8911 | L16: 8911
A17: MSW - Landfill Gas | B17: 2007 | C17: 30 | D17: 3 | E17: 1402 | F17: 1.07 | G17: 1 | H17: 1500 | I17: 0.01 | J17: 101.07 | K17: 13648 | L17: 13648
... A22: Photovoltaic7 | B22: 2006 | C22: 5 | D22: 2 | E22: 3868 | F22: 1.05 | G22: 1.1 | H22: 4467 | I22: 0 | J22: 10.34 | K22: 10280 | L22: 10280
A23: 1Online year represents the first year that a new unit could be completed, given an order date of 2004. 2The technological optimism factor is applied to the first four units of a new, unproven design, it reflects the demonstrated tendency to underestimate actual costs for a first-of-a-kind unit. 3Overnight capital cost including contingency factors, excluding regional multipliers and learning effects. Interest charges are also excluded. These represent costs of new projects initiated in 2004. 4O&M = Operations and maintenance. 5Combustion turbine units can be built by the model prior to 2006 if necessary to meet a given region’s reserve margin. 6Because geothermal and hydro cost and performance characteristics are specific for each site, the table entries represent the cost of the least expensive plant that could be built in the Northwest Power Pool region, where most of the proposed sites are located. 7Capital costs for geothermal and solar technologies are shown before the 10 percent investment tax credit is applied.
A24: Sources: The values shown in this table are developed by the Energy Information Administration, Office of Integrated Analysis and Forecasting, from analysis of reports and discussions with various sources from industry, government, and the Department of Energy Fuel Offices and National Laboratories. They are not based on any specific technology model, but rather, are meant to represent the cost and performance of typical plants under normal operating conditions for each plant type. Key sources reviewed are listed in the ‘Notes and Sources’ section at the end of the chapter.

Sheet 2021
A1: Table 3. Cost and performance characteristics of new central station electricity generating technologies
A2: Technology | B2: First available year1 | C2: Size (MW) | D2: Lead time (years) | F2: Base overnight cost2 (2020 $/kW) | H2: Techno- logical optimism factor3 | I2: Total overnight cost4,5 (2020 $/kW) | K2: Variable O&M6 (2020 $/MWh) | M2: Fixed O&M (2020$/ kW-yr) | O2: Heat rate7 (Btu/kWh)
A3: Ultra-supercritical coal (USC) | B3: 2024 | C3: 650 | D3: 4 | F3: 3672 | H3: 1 | I3: 3672 | K3: 4.52 | M3: 40.79 | O3: 8638
A4: USC with 30% carbon capture and sequestration (CCS) | B4: 2024 | C4: 650 | D4: 4 | F4: 4550 | H4: 1.01 | I4: 4595 | K4: 7.11 | M4: 54.57 | O4: 9751
A5: USC with 90% CCS | B5: 2024 | C5: 650 | D5: 4 | F5: 5861 | H5: 1.02 | I5: 5978 | K5: 11.03 | M5: 59.85 | O5: 12507
A6: Combined-cycle—single shaft | B6: 2023 | C6: 418 | D6: 3 | F6: 1082 | H6: 1 | I6: 1082 | K6: 2.56 | M6: 14.17 | O6: 6431
A7: Combined-cycle—multi shaft | B7: 2023 | C7: 1083 | D7: 3 | F7: 957 | H7: 1 | I7: 957 | K7: 1.88 | M7: 12.26 | O7: 6370
A8: Combined-cycle with 90% CCS | B8: 2023 | C8: 377 | D8: 3 | F8: 2471 | H8: 1.04 | I8: 2570 | K8: 5.87 | M8: 27.74 | O8: 7124
A9: Internal combustion engine | B9: 2022 | C9: 21 | E9: 2 | G9: 1813 | H9: 1 | J9: 1813 | L9: 5.72 | N9: 35.34 | O9: 8295
A10: Combustion turbine— aeroderivative8 | B10: 2022 | C10: 105 | E10: 2 | G10: 1169 | H10: 1 | J10: 1169 | L10: 4.72 | N10: 16.38 | O10: 9124
A11: Combustion turbine—industrial | B11: 2022 | C11: 237 | E11: 2 | G11: 709 | H11: 1 | J11: 709 | L11: 4.52 | N11: 7.04 | O11: 9905
A12: frame
A13: Fuel cells | B13: 2023 | C13: 10 | E13: 3 | G13: 6277 | H13: 1.09 | J13: 6866 | L13: 0.59 | N13: 30.94 | O13: 6469
A14: Nuclear—light water reactor | B14: 2026 | C14: 2156 | E14: 6 | G14: 6034 | H14: 1.05 | J14: 6336 | L14: 2.38 | N14: 122.26 | O14: 10455
A15: Nuclear—small modular reactor | B15: 2028 | C15: 600 | E15: 6 | G15: 6183 | H15: 1.1 | J15: 6802 | L15: 3.02 | N15: 95.48 | O15: 10455
A16: Distributed generation—base | B16: 2023 | C16: 2 | E16: 3 | G16: 1560 | H16: 1 | J16: 1560 | L16: 8.65 | N16: 19.46 | O16: 8935
A17: Distributed generation—peak | B17: 2022 | C17: 1 | E17: 2 | G17: 1874 | H17: 1 | J17: 1874 | L17: 8.65 | N17: 19.46 | O17: 9921
A18: Battery storage | B18: 2021 | C18: 50 | E18: 1 | G18: 1165 | H18: 1 | J18: 1165 | L18: 0 | N18: 24.93 | O18: NA
A19: Biomass | B19: 2024 | C19: 50 | E19: 4 | G19: 4077 | H19: 1 | J19: 4078 | L19: 4.85 | N19: 126.36 | O19: 13500
A20: Geothermal9, 10 | B20: 2024 | C20: 50 | E20: 4 | G20: 2772 | H20: 1 | J20: 2772 | L20: 1.17 | N20: 137.5 | O20: 8946
A21: Municipal solid waste—landfill | B21: 2023 | C21: 36 | E21: 3 | G21: 1566 | H21: 1 | J21: 1566 | L21: 6.23 | N21: 20.2 | O21: 8513
A22: gas
A23: Conventional hydropower10 | B23: 2024 | C23: 100 | E23: 4 | G23: 2769 | H23: 1 | J23: 2769 | L23: 1.4 | N23: 42.01 | O23: NA
A24: Wind5 | B24: 2023 | C24: 200 | E24: 3 | G24: 1846 | H24: 1 | J24: 1846 | L24: 0 | N24: 26.47 | O24: NA
A25: Wind offshore9 | B25: 2024 | C25: 400 | E25: 4 | G25: 4362 | H25: 1.25 | J25: 5453 | L25: 0 | N25: 110.56 | O25: NA
A26: Solar thermal9 | B26: 2023 | C26: 115 | E26: 3 | G26: 7116 | H26: 1 | J26: 7116 | L26: 0 | N26: 85.82 | O26: NA
A27: Solar photovoltaic (PV) with tracking5, 9, 11 | B27: 2022 | C27: 150 | E27: 2 | G27: 1248 | H27: 1 | J27: 1248 | L27: 0 | N27: 15.33 | O27: NA
A28: Solar PV with storage9, 11 | B28: 2022 | C28: 150 | E28: 2 | G28: 1612 | H28: 1 | J28: 1612 | L28: 0 | N28: 32.33 | O28: NA
A29: 1 Represents the first year that a new unit could become operational. 2 Base cost includes project contingency costs. 3 The technological optimism factor is applied to the first four units of a new, unproven design; it reflects the demonstrated tendency to underestimate actual costs for a first- of-a-kind unit. 4 Overnight capital cost includes contingency factors and excludes regional multipliers (except as noted for wind and solar PV) and learning effects. Interest charges are also excluded. The capital costs represent current costs for plants that would come online in 2021. 5 Total overnight cost for wind and solar PV technologies in the table are the average input value across all 25 electricity market regions, as weighted by the respective capacity of that type installed during 2019 in each region to account for the substantial regional variation in wind and solar costs (as shown in Table 4). The input value used for onshore wind in AEO2021 was $1,268 per kilowatt (kW) and for solar PV with tracking it was $1,232/kW, which represents the cost of building a plant excluding regional factors. Region-specific factors contributing to the substantial regional variation in cost include differences in typical project size across regions, accessibility of resources, and variation in labor and other construction costs throughout the country. 6 O&M = Operations and maintenance. 7 The nuclear average heat rate is the weighted average tested heat rate for nuclear units as reported on the Form EIA-860, Annual Electric Generator Report. No heat rate is reported for battery storage because it is not a primary conversion technology; conversion losses are accounted for when the electricity is first generated; electricity-to- storage losses are accounted for through the additional demand for electricity required to meet load. For hydropower, wind, solar, and geothermal technologies, no heat rate is reported because the power is generated without fuel combustion and no set British thermal unit conversion factors exist. The model calculates the average heat rate for fossil-fuel generation in each year to report primary energy consumption displaced for these resources. 8 Combustion turbine aeroderivative units can be built by the model before 2022, if necessary, to meet a region's reserve margin. 9 Capital costs are shown before investment tax credits are applied. 10 Because geothermal and hydropower cost and performance characteristics are specific for each site, the table entries show the cost of the least expensive plant that could be built in the Northwest region for hydro and Great Basin region for geothermal, where most of the proposed sites are located. 11 Costs and capacities are expressed in terms of net AC (alternating current) power available to the grid for the installed capacity. Sources: Input costs are primarily based on a report provided by external consultants: Sargent & Lundy, December 2019. Hydropower site costs for non-powered dams were most recently updated for AEO2018 using data from Oak Ridge National Lab
A30: Table 4. Total overnight capital costs of new electricity generating technologies by region 2020 dollars per kilowatt

Sheet 2022
A1: Table 3. Cost and performance characteristics of new central station electricity generating technologies
A2: Technology | B2: First available yeara | C2: Size (MW) | D2: Lead time (years) | E2: Base overnight cost2b (2021$/kW) | F2: Techno- logical optimism factorc | G2: Total overnight costd,e (2021$/kW) | H2: Variable O&Mf (2021 $/MWh) | I2: Fixed O&M (2021$/ kW-y) | J2: Heat rateg (Btu/kWh)
A3: Ultra-supercritical coal (USC) | B3: 2025 | C3: 650 | D3: 4 | E3: 4074 | F3: 1 | G3: 4074 | H3: 4.71 | I3: 42.49 | J3: 8638
A4: USC with 30% carbon capture and sequestration (CCS) | B4: 2025 | C4: 650 | D4: 4 | E4: 5045 | F4: 1.01 | G4: 5096 | H4: 7.41 | I4: 56.84 | J4: 9751
A5: USC with 90% CCS | B5: 2025 | C5: 650 | D5: 4 | E5: 6495 | F5: 1.02 | G5: 6625 | H5: 11.49 | I5: 62.34 | J5: 12507
A6: Combined-cycle—single-shaft | B6: 2024 | C6: 418 | D6: 3 | E6: 1201 | F6: 1 | G6: 1201 | H6: 2.67 | I6: 14.76 | J6: 6431
A7: Combined-cycle—multi-shaft | B7: 2024 | C7: 1083 | D7: 3 | E7: 1062 | F7: 1 | G7: 1062 | H7: 1.96 | I7: 12.77 | J7: 6370
A8: Combined-cycle with 90% CCS | B8: 2024 | C8: 377 | D8: 3 | E8: 2736 | F8: 1.04 | G8: 2845 | H8: 6.11 | I8: 28.89 | J8: 7124
A9: Internal combustion engine | B9: 2023 | C9: 21 | D9: 2 | E9: 2018 | F9: 1 | G9: 2018 | H9: 5.96 | I9: 36.81 | J9: 8295
A10: Combustion turbine— aeroderivativeh | B10: 2023 | C10: 105 | D10: 2 | E10: 1294 | F10: 1 | G10: 1294 | H10: 4.92 | I10: 17.06 | J10: 9124
A11: Combustion turbine—industrial frame | B11: 2023 | C11: 237 | D11: 2 | E11: 785 | F11: 1 | G11: 785 | H11: 4.71 | I11: 7.33 | J11: 9905
A12: Fuel cells | B12: 2024 | C12: 10 | D12: 3 | E12: 6639 | F12: 1.09 | G12: 7224 | H12: 0.62 | I12: 32.23 | J12: 6469
A13: Nuclear—light water reactor | B13: 2027 | C13: 2156 | D13: 6 | E13: 6695 | F13: 1.05 | G13: 7030 | H13: 2.48 | I13: 127.35 | J13: 10443
A14: Nuclear—small modular reactor | B14: 2028 | C14: 600 | D14: 6 | E14: 6861 | F14: 1.1 | G14: 7547 | H14: 3.14 | I14: 99.46 | J14: 10443
... A16: Distributed generation—peak | B16: 2023 | C16: 1 | D16: 2 | E16: 2079 | F16: 1 | G16: 2079 | H16: 9.01 | I16: 20.27 | J16: 9907
A17: Battery storage | B17: 2022 | C17: 50 | D17: 1 | E17: 1316 | F17: 1 | G17: 1316 | H17: 0 | I17: 25.96 | J17: NA
A18: Biomass | B18: 2025 | C18: 50 | D18: 4 | E18: 4524 | F18: 1 | G18: 4525 | H18: 5.06 | I18: 131.62 | J18: 13500
A19: Geothermali, j | B19: 2025 | C19: 50 | D19: 4 | E19: 3076 | F19: 1 | G19: 3076 | H19: 1.21 | I19: 143.22 | J19: 8813
A20: Conventional hydropowerj | B20: 2025 | C20: 100 | D20: 4 | E20: 3083 | F20: 1 | G20: 3083 | H20: 1.46 | I20: 43.78 | J20: NA
A21: Winde | B21: 2024 | C21: 200 | D21: 3 | E21: 1718 | F21: 1 | G21: 1718 | H21: 0 | I21: 27.57 | J21: NA
A22: Wind offshorei | B22: 2025 | C22: 400 | D22: 4 | E22: 4833 | F22: 1.25 | G22: 6041 | H22: 0 | I22: 115.16 | J22: NA
A23: Solar thermali | B23: 2024 | C23: 115 | D23: 3 | E23: 7895 | F23: 1 | G23: 7895 | H23: 0 | I23: 89.39 | J23: NA
A24: Solar photovoltaic (PV) with trackinge, i, k | B24: 2023 | C24: 150 | D24: 2 | E24: 1327 | F24: 1 | G24: 1327 | H24: 0 | I24: 15.97 | J24: NA
A25: Solar PV with storagei, k | B25: 2023 | C25: 150 | D25: 2 | E25: 1748 | F25: 1 | G25: 1748 | H25: 0 | I25: 33.67 | J25: NA
A26: Source: We primarily base input costs on a report provided by external consultants: Sargent & Lundy, December 2019. We most recently updated hydropower site costs for non-powered dams for AEO2018 using data from Oak Ridge National Lab Note: MW=megawatt, kW=kilowatt, MWh=megawatthour, kW-y=kilowatt-year, kWh=kilowatthour; Btu=British thermal unit a The first year that a new unit could become operational. b Base cost includes project contingency costs. c We apply the technological optimism factor to the first four units of a new, unproven design; it reflects the demonstrated tendency to underestimate actual costs for a first- of-a-kind unit. d Overnight capital cost includes contingency factors and excludes regional multipliers (except as noted for wind and solar PV) and learning effects. Interest charges are also excluded. The capital costs represent current costs for plants that would come online in 2022. e Total overnight cost for wind and solar PV technologies in the table are the average input value across all 25 electricity market regions, as weighted by the respective capacity of that type installed during 2020 in each region to account for the substantial regional variation in wind and solar costs (Table 4). The input value used for onshore wind in AEO2022 was $1,411 per kilowatt (kW), and for solar PV with tracking, it was $1,323/kW, which represents the cost of building a plant excluding regional factors. Region-specific factors contributing to the substantial regional variation in cost include differences in typical project size across regions, accessibility of resources, and variation in labor and other construction costs throughout the country. f O&M = Operations and maintenance. g The nuclear average heat rate is the weighted average tested heat rate for nuclear units as reported on the Form EIA-860, Annual Electric Generator Report. No heat rate is reported for battery storage because it is not a primary conversion technology; conversion losses are accounted for when the electricity is first generated; electricity-to- storage losses are accounted for through the additional demand for electricity required to meet load. For hydropower, wind, solar, and geothermal technologies, no heat rate is reported because the power is generated without fuel combustion, and no set British thermal unit conversion factors exist. The module calculates the average heat rate for fossil-fuel generation in each year to report primary energy consumption displaced for these resources. h Combustion turbine aeroderivative units can be built by the module before 2023, if necessary, to meet a region's reserve margin. i Capital costs are shown before investment tax credits are applied. j Because geothermal and hydropower cost and performance characteristics are specific for each site, the table entries show the cost of the least expensive plant that could be built in the Northwest region for hydro and the Great Basin region for geothermal, where most of the proposed sites are located. k Costs and capacities are expressed in terms of net AC (alternating current) power available to the grid for the installed capacity.

Sheet entry to fco ratio
A1: Scrubbed Coal New | B1: ='Combined, overhead'!B3/'Combined, O&M'!B3 -> 47.459835 | C1: ='Combined, overhead'!C3/'Combined, O&M'!C3 -> 47.85063 | P1: ='Combined, overhead'!P3/'Combined, O&M'!P3 -> #DIV/0! | Q1: ='Combined, overhead'!Q3/'Combined, O&M'!Q3 -> 87.684413 | R1: ='Combined, overhead'!R3/'Combined, O&M'!R3 -> 87.483954
A2: Integrated Coal- Gasification Comb Cycle (IGCC) | B2: ='Combined, overhead'!B4/'Combined, O&M'!B4 -> 33.955805 | C2: ='Combined, overhead'!C4/'Combined, O&M'!C4 -> 40.927482 | P2: ='Combined, overhead'!P4/'Combined, O&M'!P4 -> #DIV/0! | Q2: ='Combined, overhead'!Q4/'Combined, O&M'!Q4 -> 68.593112 | R2: ='Combined, overhead'!R4/'Combined, O&M'!R4 -> 67.802219
A3: Conv Gas/Oil Comb Cycle | B3: ='Combined, overhead'!B5/'Combined, O&M'!B5 -> 28.990228 | C3: ='Combined, overhead'!C5/'Combined, O&M'!C5 -> 29.250814 | P3: ='Combined, overhead'!P5/'Combined, O&M'!P5 -> #DIV/0! | Q3: ='Combined, overhead'!Q5/'Combined, O&M'!Q5 -> 66.135156 | R3: ='Combined, overhead'!R5/'Combined, O&M'!R5 -> 66.033435 | S3: ='Combined, overhead'!S5/'Combined, O&M'!S5 -> 88.847584 | T3: ='Combined, overhead'!T5/'Combined, O&M'!T5 -> 84.446478 | U3: ='Combined, overhead'!U5/'Combined, O&M'!U5 -> 84.158416 | V3: ='Combined, overhead'!V5/'Combined, O&M'!V5 -> 84.024713
A4: Combined-cycle—single shaft | B4: ='Combined, overhead'!B6/'Combined, O&M'!B6 -> #DIV/0! | C4: ='Combined, overhead'!C6/'Combined, O&M'!C6 -> #DIV/0! | P4: ='Combined, overhead'!P6/'Combined, O&M'!P6 -> #DIV/0! | W4: ='Combined, overhead'!W6/'Combined, O&M'!W6 -> 76.851852 | X4: ='Combined, overhead'!X6/'Combined, O&M'!X6 -> 76.358504
A5: Adv Gas/Oil Comb Cycle (CC) | B5: ='Combined, overhead'!B7/'Combined, O&M'!B7 -> 28.460998 | C5: ='Combined, overhead'!C7/'Combined, O&M'!C7 -> 40.75896 | P5: ='Combined, overhead'!P7/'Combined, O&M'!P7 -> #DIV/0! | Q5: ='Combined, overhead'!Q7/'Combined, O&M'!Q7 -> 61.483409 | R5: ='Combined, overhead'!R7/'Combined, O&M'!R7 -> 61.328125 | S5: ='Combined, overhead'!S7/'Combined, O&M'!S7 -> 110.42945 | T5: ='Combined, overhead'!T7/'Combined, O&M'!T7 -> 101.91147 | U5: ='Combined, overhead'!U7/'Combined, O&M'!U7 -> 101.58416 | V5: ='Combined, overhead'!V7/'Combined, O&M'!V7 -> 71.456311
A6: Combined-cycle—multi shaft | B6: ='Combined, overhead'!B8/'Combined, O&M'!B8 -> #DIV/0! | C6: ='Combined, overhead'!C8/'Combined, O&M'!C8 -> #DIV/0! | P6: ='Combined, overhead'!P8/'Combined, O&M'!P8 -> #DIV/0! | W6: ='Combined, overhead'!W8/'Combined, O&M'!W8 -> 78.518519 | X6: ='Combined, overhead'!X8/'Combined, O&M'!X8 -> 78.058728
A7: Conv Comb Turbine | B7: ='Combined, overhead'!B9/'Combined, O&M'!B9 -> 51.811024 | C7: ='Combined, overhead'!C9/'Combined, O&M'!C9 -> 52.283465 | P7: ='Combined, overhead'!P9/'Combined, O&M'!P9 -> #DIV/0! | Q7: ='Combined, overhead'!Q9/'Combined, O&M'!Q9 -> 125.88556 | R7: ='Combined, overhead'!R9/'Combined, O&M'!R9 -> 125.61308 | S7: ='Combined, overhead'!S9/'Combined, O&M'!S9 -> 62.908879 | T7: ='Combined, overhead'!T9/'Combined, O&M'!T9 -> 59.804485 | U7: ='Combined, overhead'!U9/'Combined, O&M'!U9 -> 59.649123 | V7: ='Combined, overhead'!V9/'Combined, O&M'!V9 -> 59.456461
A8: Combustion turbine— aeroderivative8 | W8: ='Combined, overhead'!W10/'Combined, O&M'!W10 -> 72.088725 | X8: ='Combined, overhead'!X10/'Combined, O&M'!X10 -> 71.367521
A9: Adv Comb Turbine | B9: ='Combined, overhead'!B11/'Combined, O&M'!B11 -> 36.071032 | C9: ='Combined, overhead'!C11/'Combined, O&M'!C11 -> 51.609323 | Q9: ='Combined, overhead'!Q11/'Combined, O&M'!Q11 -> 91.051136 | R9: ='Combined, overhead'!R11/'Combined, O&M'!R11 -> 90.767045 | S9: ='Combined, overhead'!S11/'Combined, O&M'!S11 -> 99.849624 | T9: ='Combined, overhead'!T11/'Combined, O&M'!T11 -> 94.674556 | U9: ='Combined, overhead'!U11/'Combined, O&M'!U11 -> 94.323144 | V9: ='Combined, overhead'!V11/'Combined, O&M'!V11 -> 93.865906
A10: Combustion turbine—industrial frame | W10: ='Combined, overhead'!W12/'Combined, O&M'!W12 -> 101.86514 | X10: ='Combined, overhead'!X12/'Combined, O&M'!X12 -> 100.71023
A11: Adv Nuclear | B11: ='Combined, overhead'!B13/'Combined, O&M'!B13 -> 27.891277 | C11: ='Combined, overhead'!C13/'Combined, O&M'!C13 -> 42.458696 | Q11: ='Combined, overhead'!Q13/'Combined, O&M'!Q13 -> 51.061321 | R11: ='Combined, overhead'!R13/'Combined, O&M'!R13 -> 49.833745 | S11: ='Combined, overhead'!S13/'Combined, O&M'!S13 -> 62.256651 | T11: ='Combined, overhead'!T13/'Combined, O&M'!T13 -> 51.088811 | U11: ='Combined, overhead'!U13/'Combined, O&M'!U13 -> 50.829384 | V11: ='Combined, overhead'!V13/'Combined, O&M'!V13 -> 50.566257 | W11: ='Combined, overhead'!W13/'Combined, O&M'!W13 -> 49.665648 | X11: ='Combined, overhead'!X13/'Combined, O&M'!X13 -> 49.353836
A12: Conventional Hydropower | Q12: ='Combined, overhead'!Q14/'Combined, O&M'!Q14 -> 149.22454 | R12: ='Combined, overhead'!R14/'Combined, O&M'!R14 -> 159.07591 | S12: ='Combined, overhead'!S14/'Combined, O&M'!S14 -> 164.01361 | T12: ='Combined, overhead'!T14/'Combined, O&M'!T14 -> 148.6939 | U12: ='Combined, overhead'!U14/'Combined, O&M'!U14 -> 65.76779 | V12: ='Combined, overhead'!V14/'Combined, O&M'!V14 -> 65.605875 | W12: ='Combined, overhead'!W14/'Combined, O&M'!W14 -> 66.106173 | X12: ='Combined, overhead'!X14/'Combined, O&M'!X14 -> 65.912878
A13: Wind | B13: ='Combined, overhead'!B15/'Combined, O&M'!B15 -> 29.938272 | C13: ='Combined, overhead'!C15/'Combined, O&M'!C15 -> 38.310185 | Q13: ='Combined, overhead'!Q15/'Combined, O&M'!Q15 -> 52.111252 | R13: ='Combined, overhead'!R15/'Combined, O&M'!R15 -> 46.799899 | S13: ='Combined, overhead'!S15/'Combined, O&M'!S15 -> 35.754676 | T13: ='Combined, overhead'!T15/'Combined, O&M'!T15 -> 33.740098 | U13: ='Combined, overhead'!U15/'Combined, O&M'!U15 -> 32.61007 | V13: ='Combined, overhead'!V15/'Combined, O&M'!V15 -> 31.350682 | W13: ='Combined, overhead'!W15/'Combined, O&M'!W15 -> 50.305111 | X13: ='Combined, overhead'!X15/'Combined, O&M'!X15 -> 69.739328
A14: Wind Offshore | Q14: ='Combined, overhead'!Q16/'Combined, O&M'!Q16 -> 60.851351 | R14: ='Combined, overhead'!R16/'Combined, O&M'!R16 -> 60.5192 | S14: ='Combined, overhead'!S16/'Combined, O&M'!S16 -> 83.193167 | T14: ='Combined, overhead'!T16/'Combined, O&M'!T16 -> 60.129366 | U14: ='Combined, overhead'!U16/'Combined, O&M'!U16 -> 59.750509 | V14: ='Combined, overhead'!V16/'Combined, O&M'!V16 -> 59.371101 | W14: ='Combined, overhead'!W16/'Combined, O&M'!W16 -> 39.766295 | X14: ='Combined, overhead'!X16/'Combined, O&M'!X16 -> 39.45369
A15: Solar Thermal | B15: ='Combined, overhead'!B17/'Combined, O&M'!B17 -> 40.940318 | C15: ='Combined, overhead'!C17/'Combined, O&M'!C17 -> 65.671962 | Q15: ='Combined, overhead'!Q17/'Combined, O&M'!Q17 -> 70.1011 | R15: ='Combined, overhead'!R17/'Combined, O&M'!R17 -> 56.32902 | S15: ='Combined, overhead'!S17/'Combined, O&M'!S17 -> 60.257337 | T15: ='Combined, overhead'!T17/'Combined, O&M'!T17 -> 55.621976 | U15: ='Combined, overhead'!U17/'Combined, O&M'!U17 -> 55.342389 | V15: ='Combined, overhead'!V17/'Combined, O&M'!V17 -> 55.065898 | W15: ='Combined, overhead'!W17/'Combined, O&M'!W17 -> 84.570152 | X15: ='Combined, overhead'!X17/'Combined, O&M'!X17 -> 82.917735
A16: Photovoltaic | B16: ='Combined, overhead'!B18/'Combined, O&M'!B18 -> 295.62118 | C16: ='Combined, overhead'!C18/'Combined, O&M'!C18 -> 492.46436 | Q16: ='Combined, overhead'!Q18/'Combined, O&M'!Q18 -> 137.46456 | R16: ='Combined, overhead'!R18/'Combined, O&M'!R18 -> 126.53971 | S16: ='Combined, overhead'!S18/'Combined, O&M'!S18 -> 116.26817 | T16: ='Combined, overhead'!T18/'Combined, O&M'!T18 -> 100.1385 | U16: ='Combined, overhead'!U18/'Combined, O&M'!U18 -> 80.063579 | V16: ='Combined, overhead'!V18/'Combined, O&M'!V18 -> 83.526269
A17: Photovoltaic tilting | X17: ='Combined, overhead'!X19/'Combined, O&M'!X19 -> 81.409002
A18: Solar PV with storage | X18: ='Combined, overhead'!X20/'Combined, O&M'!X20 -> 49.86081
